Workbook

Sheet Cube Index
B2: 📊 Cube Model Index
B3: Generated from WIP 4 — Brook Executive Dashboard 2026
B5: Dimensions
B6: Sheet | C6: Description | D6: Rows | E6: Key Columns
B7: dim_date | C7: Daily calendar grain for 2024–2026. Supports week (Sun–Sat) and month rollups. | D7: 1096 | E7: date_id (DDMMYY), week_start_sunday, month_name, quarter
B8: dim_kpi | C8: KPI catalog with domain, owner, unit type, cumulative flag. | D8: 24 | E8: kpi_id, domain, kpi_name, owner, unit, store_segment
B9: dim_initiative | C9: Initiative dimension across Tier 1, Product & Eng, People & Culture. | D9: 34 | E9: initiative_id, domain, initiative_name, owner, current_status
B11: Fact Tables
B12: Sheet | C12: Description | D12: Rows | E12: Key Columns
B13: fact_kpi_weekly | C13: Core numeric fact table — one row per KPI × measure × week. | D13: 910 | E13: date_id, kpi_name, measure_class, forecast_type, value, value_numeric
B14: fact_initiative_event | C14: Milestone events — one row per initiative × week with text + score. | D14: 110 | E14: date_id, initiative_id, milestone_text, status_score, status_label
B15: cube_unified | C15: Denormalized flat table joining facts + dimensions via INDEX/MATCH. Pivot-ready. | D15: 910 | E15: All fact_kpi_weekly cols + month_name, quarter, week_num, week_label, unit, is_cumulative
B17: Reference
B18: Sheet | C18: Description | D18: Rows | E18: Key Columns
B19: ref_monthly_narrative | C19: Monthly Big Picture commentary (March–December 2026). | D19: 10 | E19: month, year, narrative_text
B20: WIP 4 | C20: Original source dashboard (preserved as-is). | D20: 109 | E20: —
B22: WIP 4 (Cube) | C22: Reproduction of WIP 4 layout, fully driven by INDEX/MATCH from fact_kpi_weekly. | D22: 67 | E22: Same layout as WIP 4 — all data cells are formulas referencing the cube
B23: Schema Notes
B24: Join Keys | C24: fact_kpi_weekly.date_id → dim_date.date_id | fact_kpi_weekly.kpi_name → dim_kpi.kpi_name
C25: fact_initiative_event.initiative_id → dim_initiative.initiative_id
B26: Measure Structure | C26: measure_class (Goal / Forecast / Actual) + forecast_type (Internal / Board / Projection / blank)
B27: Status Scoring | C27: 1.0 = Complete, 0.75 = Near Complete, 0.5 = In Progress, 0.25 = Early Stage, 0.0 = Planned
B28: date_id Format | C28: YYMMDD (e.g., 260301 = March 1, 2026). Week starts Sunday.

Sheet cube_unified
A1: date_id | B1: week_start | C1: domain | D1: kpi_name | E1: measure_class | F1: forecast_type | G1: store_segment | H1: owner | I1: value | J1: value_numeric | K1: month_name | L1: month_num | M1: quarter | N1: week_num | O1: week_label | P1: unit | Q1: is_cumulative
A2: =fact_kpi_weekly!A2 -> 260301 | B2: =fact_kpi_weekly!B2 -> 46082 | C2: =fact_kpi_weekly!C2 -> Contracted Lives | D2: =fact_kpi_weekly!D2 -> Pipeline Growth - 6X Patient Count | E2: =fact_kpi_weekly!E2 -> Goal | F2: =IF(fact_kpi_weekly!F2="","",fact_kpi_weekly!F2) | G2: =fact_kpi_weekly!G2 -> N/A | H2: =fact_kpi_weekly!H2 -> John | I2: =fact_kpi_weekly!I2 -> $12M | J2: =fact_kpi_weekly!J2 -> 12000000 | K2: {=IFERROR(INDEX(dim_date!H:H,MATCH(A2,dim_date!A:A,0)),"")} -> Mar | L2: {=IFERROR(INDEX(dim_date!G:G,MATCH(A2,dim_date!A:A,0)),"")} -> 03 | M2: {=IFERROR(INDEX(dim_date!I:I,MATCH(A2,dim_date!A:A,0)),"")} -> Q1 | N2: {=IFERROR(INDEX(dim_date!K:K,MATCH(A2,dim_date!A:A,0)),"")} -> 10 | O2: {=IFERROR(INDEX(dim_date!F:F,MATCH(A2,dim_date!A:A,0)),"")} -> 3/1-3/7 | P2: {=IFERROR(INDEX(dim_kpi!E:E,MATCH(D2,dim_kpi!C:C,0)),"")} -> $ | Q2: {=IFERROR(INDEX(dim_kpi!F:F,MATCH(D2,dim_kpi!C:C,0)),"")} -> N
A3: =fact_kpi_weekly!A3 -> 260308 | B3: =fact_kpi_weekly!B3 -> 46089 | C3: =fact_kpi_weekly!C3 -> Contracted Lives | D3: =fact_kpi_weekly!D3 -> Pipeline Growth - 6X Patient Count | E3: =fact_kpi_weekly!E3 -> Goal | F3: =IF(fact_kpi_weekly!F3="","",fact_kpi_weekly!F3) | G3: =fact_kpi_weekly!G3 -> N/A | H3: =fact_kpi_weekly!H3 -> John | I3: =fact_kpi_weekly!I3 -> $12M | J3: =fact_kpi_weekly!J3 -> 12000000 | K3: {=IFERROR(INDEX(dim_date!H:H,MATCH(A3,dim_date!A:A,0)),"")} -> Mar | L3: {=IFERROR(INDEX(dim_date!G:G,MATCH(A3,dim_date!A:A,0)),"")} -> 03 | M3: {=IFERROR(INDEX(dim_date!I:I,MATCH(A3,dim_date!A:A,0)),"")} -> Q1 | N3: {=IFERROR(INDEX(dim_date!K:K,MATCH(A3,dim_date!A:A,0)),"")} -> 11 | O3: {=IFERROR(INDEX(dim_date!F:F,MATCH(A3,dim_date!A:A,0)),"")} -> 3/8-3/14 | P3: {=IFERROR(INDEX(dim_kpi!E:E,MATCH(D3,dim_kpi!C:C,0)),"")} -> $ | Q3: {=IFERROR(INDEX(dim_kpi!F:F,MATCH(D3,dim_kpi!C:C,0)),"")} -> N
A4: =fact_kpi_weekly!A4 -> 260315 | B4: =fact_kpi_weekly!B4 -> 46096 | C4: =fact_kpi_weekly!C4 -> Contracted Lives | D4: =fact_kpi_weekly!D4 -> Pipeline Growth - 6X Patient Count | E4: =fact_kpi_weekly!E4 -> Goal | F4: =IF(fact_kpi_weekly!F4="","",fact_kpi_weekly!F4) | G4: =fact_kpi_weekly!G4 -> N/A | H4: =fact_kpi_weekly!H4 -> John | I4: =fact_kpi_weekly!I4 -> $12M | J4: =fact_kpi_weekly!J4 -> 12000000 | K4: {=IFERROR(INDEX(dim_date!H:H,MATCH(A4,dim_date!A:A,0)),"")} -> Mar | L4: {=IFERROR(INDEX(dim_date!G:G,MATCH(A4,dim_date!A:A,0)),"")} -> 03 | M4: {=IFERROR(INDEX(dim_date!I:I,MATCH(A4,dim_date!A:A,0)),"")} -> Q1 | N4: {=IFERROR(INDEX(dim_date!K:K,MATCH(A4,dim_date!A:A,0)),"")} -> 12 | O4: {=IFERROR(INDEX(dim_date!F:F,MATCH(A4,dim_date!A:A,0)),"")} -> 3/15-3/21 | P4: {=IFERROR(INDEX(dim_kpi!E:E,MATCH(D4,dim_kpi!C:C,0)),"")} -> $ | Q4: {=IFERROR(INDEX(dim_kpi!F:F,MATCH(D4,dim_kpi!C:C,0)),"")} -> N
A5: =fact_kpi_weekly!A5 -> 260322 | B5: =fact_kpi_weekly!B5 -> 46103 | C5: =fact_kpi_weekly!C5 -> Contracted Lives | D5: =fact_kpi_weekly!D5 -> Pipeline Growth - 6X Patient Count | E5: =fact_kpi_weekly!E5 -> Goal | F5: =IF(fact_kpi_weekly!F5="","",fact_kpi_weekly!F5) | G5: =fact_kpi_weekly!G5 -> N/A | H5: =fact_kpi_weekly!H5 -> John | I5: =fact_kpi_weekly!I5 -> $12M | J5: =fact_kpi_weekly!J5 -> 12000000 | K5: {=IFERROR(INDEX(dim_date!H:H,MATCH(A5,dim_date!A:A,0)),"")} -> Mar | L5: {=IFERROR(INDEX(dim_date!G:G,MATCH(A5,dim_date!A:A,0)),"")} -> 03 | M5: {=IFERROR(INDEX(dim_date!I:I,MATCH(A5,dim_date!A:A,0)),"")} -> Q1 | N5: {=IFERROR(INDEX(dim_date!K:K,MATCH(A5,dim_date!A:A,0)),"")} -> 13 | O5: {=IFERROR(INDEX(dim_date!F:F,MATCH(A5,dim_date!A:A,0)),"")} -> 3/22-3/28 | P5: {=IFERROR(INDEX(dim_kpi!E:E,MATCH(D5,dim_kpi!C:C,0)),"")} -> $ | Q5: {=IFERROR(INDEX(dim_kpi!F:F,MATCH(D5,dim_kpi!C:C,0)),"")} -> N
A6: =fact_kpi_weekly!A6 -> 260329 | B6: =fact_kpi_weekly!B6 -> 46110 | C6: =fact_kpi_weekly!C6 -> Contracted Lives | D6: =fact_kpi_weekly!D6 -> Pipeline Growth - 6X Patient Count | E6: =fact_kpi_weekly!E6 -> Goal | F6: =IF(fact_kpi_weekly!F6="","",fact_kpi_weekly!F6) | G6: =fact_kpi_weekly!G6 -> N/A | H6: =fact_kpi_weekly!H6 -> John | I6: =fact_kpi_weekly!I6 -> $12M | J6: =fact_kpi_weekly!J6 -> 12000000 | K6: {=IFERROR(INDEX(dim_date!H:H,MATCH(A6,dim_date!A:A,0)),"")} -> Mar | L6: {=IFERROR(INDEX(dim_date!G:G,MATCH(A6,dim_date!A:A,0)),"")} -> 03 | M6: {=IFERROR(INDEX(dim_date!I:I,MATCH(A6,dim_date!A:A,0)),"")} -> Q1 | N6: {=IFERROR(INDEX(dim_date!K:K,MATCH(A6,dim_date!A:A,0)),"")} -> 14 | O6: {=IFERROR(INDEX(dim_date!F:F,MATCH(A6,dim_date!A:A,0)),"")} -> 3/29-4/4 | P6: {=IFERROR(INDEX(dim_kpi!E:E,MATCH(D6,dim_kpi!C:C,0)),"")} -> $ | Q6: {=IFERROR(INDEX(dim_kpi!F:F,MATCH(D6,dim_kpi!C:C,0)),"")} -> N
A7: =fact_kpi_weekly!A7 -> 260405 | B7: =fact_kpi_weekly!B7 -> 46117 | C7: =fact_kpi_weekly!C7 -> Contracted Lives | D7: =fact_kpi_weekly!D7 -> Pipeline Growth - 6X Patient Count | E7: =fact_kpi_weekly!E7 -> Goal | F7: =IF(fact_kpi_weekly!F7="","",fact_kpi_weekly!F7) | G7: =fact_kpi_weekly!G7 -> N/A | H7: =fact_kpi_weekly!H7 -> John | I7: =fact_kpi_weekly!I7 -> $12M | J7: =fact_kpi_weekly!J7 -> 12000000 | K7: {=IFERROR(INDEX(dim_date!H:H,MATCH(A7,dim_date!A:A,0)),"")} -> Apr | L7: {=IFERROR(INDEX(dim_date!G:G,MATCH(A7,dim_date!A:A,0)),"")} -> 04 | M7: {=IFERROR(INDEX(dim_date!I:I,MATCH(A7,dim_date!A:A,0)),"")} -> Q2 | N7: {=IFERROR(INDEX(dim_date!K:K,MATCH(A7,dim_date!A:A,0)),"")} -> 15 | O7: {=IFERROR(INDEX(dim_date!F:F,MATCH(A7,dim_date!A:A,0)),"")} -> 4/5-4/11 | P7: {=IFERROR(INDEX(dim_kpi!E:E,MATCH(D7,dim_kpi!C:C,0)),"")} -> $ | Q7: {=IFERROR(INDEX(dim_kpi!F:F,MATCH(D7,dim_kpi!C:C,0)),"")} -> N
A8: =fact_kpi_weekly!A8 -> 260412 | B8: =fact_kpi_weekly!B8 -> 46124 | C8: =fact_kpi_weekly!C8 -> Contracted Lives | D8: =fact_kpi_weekly!D8 -> Pipeline Growth - 6X Patient Count | E8: =fact_kpi_weekly!E8 -> Goal | F8: =IF(fact_kpi_weekly!F8="","",fact_kpi_weekly!F8) | G8: =fact_kpi_weekly!G8 -> N/A | H8: =fact_kpi_weekly!H8 -> John | I8: =fact_kpi_weekly!I8 -> $12M | J8: =fact_kpi_weekly!J8 -> 12000000 | K8: {=IFERROR(INDEX(dim_date!H:H,MATCH(A8,dim_date!A:A,0)),"")} -> Apr | L8: {=IFERROR(INDEX(dim_date!G:G,MATCH(A8,dim_date!A:A,0)),"")} -> 04 | M8: {=IFERROR(INDEX(dim_date!I:I,MATCH(A8,dim_date!A:A,0)),"")} -> Q2 | N8: {=IFERROR(INDEX(dim_date!K:K,MATCH(A8,dim_date!A:A,0)),"")} -> 16 | O8: {=IFERROR(INDEX(dim_date!F:F,MATCH(A8,dim_date!A:A,0)),"")} -> 4/12-4/18 | P8: {=IFERROR(INDEX(dim_kpi!E:E,MATCH(D8,dim_kpi!C:C,0)),"")} -> $ | Q8: {=IFERROR(INDEX(dim_kpi!F:F,MATCH(D8,dim_kpi!C:C,0)),"")} -> N
A9: =fact_kpi_weekly!A9 -> 260419 | B9: =fact_kpi_weekly!B9 -> 46131 | C9: =fact_kpi_weekly!C9 -> Contracted Lives | D9: =fact_kpi_weekly!D9 -> Pipeline Growth - 6X Patient Count | E9: =fact_kpi_weekly!E9 -> Goal | F9: =IF(fact_kpi_weekly!F9="","",fact_kpi_weekly!F9) | G9: =fact_kpi_weekly!G9 -> N/A | H9: =fact_kpi_weekly!H9 -> John | I9: =fact_kpi_weekly!I9 -> $12M | J9: =fact_kpi_weekly!J9 -> 12000000 | K9: {=IFERROR(INDEX(dim_date!H:H,MATCH(A9,dim_date!A:A,0)),"")} -> Apr | L9: {=IFERROR(INDEX(dim_date!G:G,MATCH(A9,dim_date!A:A,0)),"")} -> 04 | M9: {=IFERROR(INDEX(dim_date!I:I,MATCH(A9,dim_date!A:A,0)),"")} -> Q2 | N9: {=IFERROR(INDEX(dim_date!K:K,MATCH(A9,dim_date!A:A,0)),"")} -> 17 | O9: {=IFERROR(INDEX(dim_date!F:F,MATCH(A9,dim_date!A:A,0)),"")} -> 4/19-4/25 | P9: {=IFERROR(INDEX(dim_kpi!E:E,MATCH(D9,dim_kpi!C:C,0)),"")} -> $ | Q9: {=IFERROR(INDEX(dim_kpi!F:F,MATCH(D9,dim_kpi!C:C,0)),"")} -> N
A10: =fact_kpi_weekly!A10 -> 260426 | B10: =fact_kpi_weekly!B10 -> 46138 | C10: =fact_kpi_weekly!C10 -> Contracted Lives | D10: =fact_kpi_weekly!D10 -> Pipeline Growth - 6X Patient Count | E10: =fact_kpi_weekly!E10 -> Goal | F10: =IF(fact_kpi_weekly!F10="","",fact_kpi_weekly!F10) | G10: =fact_kpi_weekly!G10 -> N/A | H10: =fact_kpi_weekly!H10 -> John | I10: =fact_kpi_weekly!I10 -> $12M | J10: =fact_kpi_weekly!J10 -> 12000000 | K10: {=IFERROR(INDEX(dim_date!H:H,MATCH(A10,dim_date!A:A,0)),"")} -> Apr | L10: {=IFERROR(INDEX(dim_date!G:G,MATCH(A10,dim_date!A:A,0)),"")} -> 04 | M10: {=IFERROR(INDEX(dim_date!I:I,MATCH(A10,dim_date!A:A,0)),"")} -> Q2 | N10: {=IFERROR(INDEX(dim_date!K:K,MATCH(A10,dim_date!A:A,0)),"")} -> 18 | O10: {=IFERROR(INDEX(dim_date!F:F,MATCH(A10,dim_date!A:A,0)),"")} -> 4/26-5/2 | P10: {=IFERROR(INDEX(dim_kpi!E:E,MATCH(D10,dim_kpi!C:C,0)),"")} -> $ | Q10: {=IFERROR(INDEX(dim_kpi!F:F,MATCH(D10,dim_kpi!C:C,0)),"")} -> N
A11: =fact_kpi_weekly!A11 -> 260503 | B11: =fact_kpi_weekly!B11 -> 46145 | C11: =fact_kpi_weekly!C11 -> Contracted Lives | D11: =fact_kpi_weekly!D11 -> Pipeline Growth - 6X Patient Count | E11: =fact_kpi_weekly!E11 -> Goal | F11: =IF(fact_kpi_weekly!F11="","",fact_kpi_weekly!F11) | G11: =fact_kpi_weekly!G11 -> N/A | H11: =fact_kpi_weekly!H11 -> John | I11: =fact_kpi_weekly!I11 -> $13M | J11: =fact_kpi_weekly!J11 -> 13000000 | K11: {=IFERROR(INDEX(dim_date!H:H,MATCH(A11,dim_date!A:A,0)),"")} -> May | L11: {=IFERROR(INDEX(dim_date!G:G,MATCH(A11,dim_date!A:A,0)),"")} -> 05 | M11: {=IFERROR(INDEX(dim_date!I:I,MATCH(A11,dim_date!A:A,0)),"")} -> Q2 | N11: {=IFERROR(INDEX(dim_date!K:K,MATCH(A11,dim_date!A:A,0)),"")} -> 19 | O11: {=IFERROR(INDEX(dim_date!F:F,MATCH(A11,dim_date!A:A,0)),"")} -> 5/3-5/9 | P11: {=IFERROR(INDEX(dim_kpi!E:E,MATCH(D11,dim_kpi!C:C,0)),"")} -> $ | Q11: {=IFERROR(INDEX(dim_kpi!F:F,MATCH(D11,dim_kpi!C:C,0)),"")} -> N
A12: =fact_kpi_weekly!A12 -> 260510 | B12: =fact_kpi_weekly!B12 -> 46152 | C12: =fact_kpi_weekly!C12 -> Contracted Lives | D12: =fact_kpi_weekly!D12 -> Pipeline Growth - 6X Patient Count | E12: =fact_kpi_weekly!E12 -> Goal | F12: =IF(fact_kpi_weekly!F12="","",fact_kpi_weekly!F12) | G12: =fact_kpi_weekly!G12 -> N/A | H12: =fact_kpi_weekly!H12 -> John | I12: =fact_kpi_weekly!I12 -> $13M | J12: =fact_kpi_weekly!J12 -> 13000000 | K12: {=IFERROR(INDEX(dim_date!H:H,MATCH(A12,dim_date!A:A,0)),"")} -> May | L12: {=IFERROR(INDEX(dim_date!G:G,MATCH(A12,dim_date!A:A,0)),"")} -> 05 | M12: {=IFERROR(INDEX(dim_date!I:I,MATCH(A12,dim_date!A:A,0)),"")} -> Q2 | N12: {=IFERROR(INDEX(dim_date!K:K,MATCH(A12,dim_date!A:A,0)),"")} -> 20 | O12: {=IFERROR(INDEX(dim_date!F:F,MATCH(A12,dim_date!A:A,0)),"")} -> 5/10-5/16 | P12: {=IFERROR(INDEX(dim_kpi!E:E,MATCH(D12,dim_kpi!C:C,0)),"")} -> $ | Q12: {=IFERROR(INDEX(dim_kpi!F:F,MATCH(D12,dim_kpi!C:C,0)),"")} -> N
A13: =fact_kpi_weekly!A13 -> 260517 | B13: =fact_kpi_weekly!B13 -> 46159 | C13: =fact_kpi_weekly!C13 -> Contracted Lives | D13: =fact_kpi_weekly!D13 -> Pipeline Growth - 6X Patient Count | E13: =fact_kpi_weekly!E13 -> Goal | F13: =IF(fact_kpi_weekly!F13="","",fact_kpi_weekly!F13) | G13: =fact_kpi_weekly!G13 -> N/A | H13: =fact_kpi_weekly!H13 -> John | I13: =fact_kpi_weekly!I13 -> $13M | J13: =fact_kpi_weekly!J13 -> 13000000 | K13: {=IFERROR(INDEX(dim_date!H:H,MATCH(A13,dim_date!A:A,0)),"")} -> May | L13: {=IFERROR(INDEX(dim_date!G:G,MATCH(A13,dim_date!A:A,0)),"")} -> 05 | M13: {=IFERROR(INDEX(dim_date!I:I,MATCH(A13,dim_date!A:A,0)),"")} -> Q2 | N13: {=IFERROR(INDEX(dim_date!K:K,MATCH(A13,dim_date!A:A,0)),"")} -> 21 | O13: {=IFERROR(INDEX(dim_date!F:F,MATCH(A13,dim_date!A:A,0)),"")} -> 5/17-5/23 | P13: {=IFERROR(INDEX(dim_kpi!E:E,MATCH(D13,dim_kpi!C:C,0)),"")} -> $ | Q13: {=IFERROR(INDEX(dim_kpi!F:F,MATCH(D13,dim_kpi!C:C,0)),"")} -> N
... A911: =fact_kpi_weekly!A911 -> 260517 | B911: =fact_kpi_weekly!B911 -> 46159 | C911: =fact_kpi_weekly!C911 -> Care Delivery | D911: =fact_kpi_weekly!D911 -> Optimization of Care Delivery Time to Billed | E911: =fact_kpi_weekly!E911 -> Actual | F911: =IF(fact_kpi_weekly!F911="","",fact_kpi_weekly!F911) | G911: =fact_kpi_weekly!G911 -> N/A | H911: =fact_kpi_weekly!H911 -> Alex & Kit | I911: =fact_kpi_weekly!I911 -> 0.86 | J911: =fact_kpi_weekly!J911 -> 0.86 | K911: {=IFERROR(INDEX(dim_date!H:H,MATCH(A911,dim_date!A:A,0)),"")} -> May | L911: {=IFERROR(INDEX(dim_date!G:G,MATCH(A911,dim_date!A:A,0)),"")} -> 05 | M911: {=IFERROR(INDEX(dim_date!I:I,MATCH(A911,dim_date!A:A,0)),"")} -> Q2 | N911: {=IFERROR(INDEX(dim_date!K:K,MATCH(A911,dim_date!A:A,0)),"")} -> 21 | O911: {=IFERROR(INDEX(dim_date!F:F,MATCH(A911,dim_date!A:A,0)),"")} -> 5/17-5/23 | P911: {=IFERROR(INDEX(dim_kpi!E:E,MATCH(D911,dim_kpi!C:C,0)),"")} -> % | Q911: {=IFERROR(INDEX(dim_kpi!F:F,MATCH(D911,dim_kpi!C:C,0)),"")} -> N

Sheet dim_date
A1: date_id | B1: date | C1: day_of_week | D1: week_start_sunday | E1: week_end_saturday | F1: week_label | G1: month_num | H1: month_name | I1: quarter | J1: year | K1: week_num | M1: ← Back to Cube Index
A2: 240101 | B2: 45292 | C2: Mon | D2: 45291 | E2: 45297 | F2: 12/31-1/6 | G2: 01 | H2: Jan | I2: Q1 | J2: 2024 | K2: 01
A3: 240102 | B3: 45293 | C3: Tue | D3: 45291 | E3: 45297 | F3: 12/31-1/6 | G3: 01 | H3: Jan | I3: Q1 | J3: 2024 | K3: 01
A4: 240103 | B4: 45294 | C4: Wed | D4: 45291 | E4: 45297 | F4: 12/31-1/6 | G4: 01 | H4: Jan | I4: Q1 | J4: 2024 | K4: 01
A5: 240104 | B5: 45295 | C5: Thu | D5: 45291 | E5: 45297 | F5: 12/31-1/6 | G5: 01 | H5: Jan | I5: Q1 | J5: 2024 | K5: 01
A6: 240105 | B6: 45296 | C6: Fri | D6: 45291 | E6: 45297 | F6: 12/31-1/6 | G6: 01 | H6: Jan | I6: Q1 | J6: 2024 | K6: 01
A7: 240106 | B7: 45297 | C7: Sat | D7: 45291 | E7: 45297 | F7: 12/31-1/6 | G7: 01 | H7: Jan | I7: Q1 | J7: 2024 | K7: 01
A8: 240107 | B8: 45298 | C8: Sun | D8: 45298 | E8: 45304 | F8: 1/7-1/13 | G8: 01 | H8: Jan | I8: Q1 | J8: 2024 | K8: 02
A9: 240108 | B9: 45299 | C9: Mon | D9: 45298 | E9: 45304 | F9: 1/7-1/13 | G9: 01 | H9: Jan | I9: Q1 | J9: 2024 | K9: 02
A10: 240109 | B10: 45300 | C10: Tue | D10: 45298 | E10: 45304 | F10: 1/7-1/13 | G10: 01 | H10: Jan | I10: Q1 | J10: 2024 | K10: 02
A11: 240110 | B11: 45301 | C11: Wed | D11: 45298 | E11: 45304 | F11: 1/7-1/13 | G11: 01 | H11: Jan | I11: Q1 | J11: 2024 | K11: 02
A12: 240111 | B12: 45302 | C12: Thu | D12: 45298 | E12: 45304 | F12: 1/7-1/13 | G12: 01 | H12: Jan | I12: Q1 | J12: 2024 | K12: 02
A13: 240112 | B13: 45303 | C13: Fri | D13: 45298 | E13: 45304 | F13: 1/7-1/13 | G13: 01 | H13: Jan | I13: Q1 | J13: 2024 | K13: 02
... A1097: 261231 | B1097: 46387 | C1097: Thu | D1097: 46383 | E1097: 46389 | F1097: 12/27-1/2 | G1097: 12 | H1097: Dec | I1097: Q4 | J1097: 2026 | K1097: 53

Sheet dim_kpi
A1: kpi_id | B1: domain | C1: kpi_name | D1: owner | E1: unit | F1: is_cumulative | G1: store_segment | H1: source_rows_wip4 | K1: ← Back to Cube Index
A2: KPI-01 | B2: Contracted Lives | C2: Pipeline Growth - 6X Patient Count | D2: John | E2: $ | F2: N | G2: N/A | H2: 15-16
A3: KPI-02 | B3: Contracted Lives | C3: Pipeline Growth - 6X Revenue | D3: John | E3: $ | F3: N | G3: N/A | H3: 17-18
A4: KPI-03 | B4: Contracted Lives | C4: Deals Completed | D4: John | E4: text | F4: N | G4: N/A | H4: 19-20
A5: KPI-04 | B5: Contracted Lives | C5: Implementations Completed | D5: John & Sheila | E5: text | F5: N | G5: N/A | H5: 21-00
A6: KPI-05 | B6: Contracted Lives | C6: Eligible Forecast - Total Cumulative | D6: John / Sheila | E6: count | F6: Y | G6: Total | H6: 22-23
A7: KPI-06 | B7: Contracted Lives | C7: Eligible Forecast - New Store Cumulative | D7: John / Sheila | E7: count | F7: Y | G7: New Store | H7: 24-25
A8: KPI-07 | B8: Contracted Lives | C8: Eligible Forecast - Same Store Cumulative | D8: John / Sheila | E8: count | F8: Y | G8: Same Store | H8: 26-27
A9: KPI-08 | B9: Growth | C9: Marketable Patients - Accumulated | D9: Sheila | E9: count | F9: Y | G9: N/A | H9: 29-30
A10: KPI-09 | B10: Growth | C10: New Marketable Patients - New Store | D10: John | E10: count | F10: N | G10: New Store | H10: 31-32
A11: KPI-10 | B11: Growth | C11: New Marketable Patients - Same Store | D11: Sheila | E11: count | F11: N | G11: Same Store | H11: 33-34
A12: KPI-11 | B12: Growth | C12: Conversion Rate | D12: Luke | E12: % | F12: N | G12: N/A | H12: 35-36
A13: KPI-12 | B13: Growth | C13: Total Activations | D13: Luke | E13: count | F13: N | G13: N/A | H13: 37-40
... A25: KPI-24 | B25: Care Delivery | C25: Optimization of Care Delivery Time to Billed | D25: Alex & Kit | E25: % | F25: N | G25: N/A | H25: 66-00

Sheet dim_initiative
A1: initiative_id | B1: domain | C1: initiative_name | D1: owner | E1: current_status | H1: ← Back to Cube Index
A2: TIE-01 | B2: Tier 1 Initiative | C2: RPM 2026 (new codes) | D2: Team
A3: TIE-02 | B3: Tier 1 Initiative | C3: APCM | D3: Team
A4: TIE-03 | B4: Tier 1 Initiative | C4: RPM/PCM/CCM Product and onboarding | D4: Team
A5: TIE-04 | B5: Tier 1 Initiative | C5: Griffin CCM transition and growth | D5: Sheila & Luke
A6: TIE-05 | B6: Tier 1 Initiative | C6: Brook+ acquisition | D6: Luke & Kit
A7: TIE-06 | B7: Tier 1 Initiative | C7: Care - Optimization -> Automation | D7: Alex & Kit
A8: TIE-07 | B8: Tier 1 Initiative | C8: Acquisition and Onboarding system | D8: Luke & Kit
A9: TIE-08 | B9: Tier 1 Initiative | C9: Patient retention | D9: Kit
A10: TIE-09 | B10: Tier 1 Initiative | C10: Med Management | D10: Team
A11: PRO-01 | B11: Product & Engineering | C11: RPM 2026 (new codes) | D11: Kit
A12: PRO-02 | B12: Product & Engineering | C12: APCM | D12: Kit & Alex
A13: PRO-03 | B13: Product & Engineering | C13: PCM/CCM | D13: Kit & Alex
... A29: PRO-19 | B29: Product & Engineering | C29: Patient satisfaction | D29: Kit
A30: PEO-01 | B30: People & Culture | C30: Avg time posted to offer - Leadership | D30: Tricia | E30: Less than 75 days
A31: PEO-02 | B31: People & Culture | C31: Avg time posted to offer - Technical | D31: Tricia | E31: Less than 60 days
A32: PEO-03 | B32: People & Culture | C32: Avg time posted to offer - IC | D32: Tricia | E32: Less than 45 days
A33: PEO-04 | B33: People & Culture | C33: Employee Regrettable Turnover | D33: Tricia | E33: Annualized under 15%
A34: PEO-05 | B34: People & Culture | C34: Employee Regrettable Turnover under 1 year | D34: Tricia | E34: Annualized under 10%
A35: PEO-06 | B35: People & Culture | C35: HR Calendar | D35: Tricia

Sheet fact_kpi_weekly
A1: date_id | B1: week_start | C1: domain | D1: kpi_name | E1: measure_class | F1: forecast_type | G1: store_segment | H1: owner | I1: value | J1: value_numeric | M1: ← Back to Cube Index
A2: 260301 | B2: 46082 | C2: Contracted Lives | D2: Pipeline Growth - 6X Patient Count | E2: Goal | G2: N/A | H2: John | I2: $12M | J2: 12000000
A3: 260308 | B3: 46089 | C3: Contracted Lives | D3: Pipeline Growth - 6X Patient Count | E3: Goal | G3: N/A | H3: John | I3: $12M | J3: 12000000
A4: 260315 | B4: 46096 | C4: Contracted Lives | D4: Pipeline Growth - 6X Patient Count | E4: Goal | G4: N/A | H4: John | I4: $12M | J4: 12000000
A5: 260322 | B5: 46103 | C5: Contracted Lives | D5: Pipeline Growth - 6X Patient Count | E5: Goal | G5: N/A | H5: John | I5: $12M | J5: 12000000
A6: 260329 | B6: 46110 | C6: Contracted Lives | D6: Pipeline Growth - 6X Patient Count | E6: Goal | G6: N/A | H6: John | I6: $12M | J6: 12000000
A7: 260405 | B7: 46117 | C7: Contracted Lives | D7: Pipeline Growth - 6X Patient Count | E7: Goal | G7: N/A | H7: John | I7: $12M | J7: 12000000
A8: 260412 | B8: 46124 | C8: Contracted Lives | D8: Pipeline Growth - 6X Patient Count | E8: Goal | G8: N/A | H8: John | I8: $12M | J8: 12000000
A9: 260419 | B9: 46131 | C9: Contracted Lives | D9: Pipeline Growth - 6X Patient Count | E9: Goal | G9: N/A | H9: John | I9: $12M | J9: 12000000
A10: 260426 | B10: 46138 | C10: Contracted Lives | D10: Pipeline Growth - 6X Patient Count | E10: Goal | G10: N/A | H10: John | I10: $12M | J10: 12000000
A11: 260503 | B11: 46145 | C11: Contracted Lives | D11: Pipeline Growth - 6X Patient Count | E11: Goal | G11: N/A | H11: John | I11: $13M | J11: 13000000
A12: 260510 | B12: 46152 | C12: Contracted Lives | D12: Pipeline Growth - 6X Patient Count | E12: Goal | G12: N/A | H12: John | I12: $13M | J12: 13000000
A13: 260517 | B13: 46159 | C13: Contracted Lives | D13: Pipeline Growth - 6X Patient Count | E13: Goal | G13: N/A | H13: John | I13: $13M | J13: 13000000
... A93: 260315 | B93: 46096 | C93: Contracted Lives | D93: Pipeline Growth - 6X Revenue | E93: Actual | G93: N/A | H93: John | I93: $115.2M | J93: 115200000
A94: 260301 | B94: 46082 | C94: Contracted Lives | D94: Eligible Forecast - Total Cumulative | E94: Forecast | G94: Total | H94: John / Sheila | I94: 10327 | J94: 10327
A95: 260308 | B95: 46089 | C95: Contracted Lives | D95: Eligible Forecast - Total Cumulative | E95: Forecast | G95: Total | H95: John / Sheila | I95: 11827 | J95: 11827
A96: 260315 | B96: 46096 | C96: Contracted Lives | D96: Eligible Forecast - Total Cumulative | E96: Forecast | G96: Total | H96: John / Sheila | I96: 13327 | J96: 13327
A97: 260322 | B97: 46103 | C97: Contracted Lives | D97: Eligible Forecast - Total Cumulative | E97: Forecast | G97: Total | H97: John / Sheila | I97: 14827 | J97: 14827
A98: 260329 | B98: 46110 | C98: Contracted Lives | D98: Eligible Forecast - Total Cumulative | E98: Forecast | G98: Total | H98: John / Sheila | I98: 19827 | J98: 19827
A99: 260405 | B99: 46117 | C99: Contracted Lives | D99: Eligible Forecast - Total Cumulative | E99: Forecast | G99: Total | H99: John / Sheila | I99: 21327 | J99: 21327
A100: 260412 | B100: 46124 | C100: Contracted Lives | D100: Eligible Forecast - Total Cumulative | E100: Forecast | G100: Total | H100: John / Sheila | I100: 22827 | J100: 22827
A101: 260419 | B101: 46131 | C101: Contracted Lives | D101: Eligible Forecast - Total Cumulative | E101: Forecast | G101: Total | H101: John / Sheila | I101: 24327 | J101: 24327
A102: 260426 | B102: 46138 | C102: Contracted Lives | D102: Eligible Forecast - Total Cumulative | E102: Forecast | G102: Total | H102: John / Sheila | I102: 40827 | J102: 40827
A103: 260503 | B103: 46145 | C103: Contracted Lives | D103: Eligible Forecast - Total Cumulative | E103: Forecast | G103: Total | H103: John / Sheila | I103: 42327 | J103: 42327
A104: 260510 | B104: 46152 | C104: Contracted Lives | D104: Eligible Forecast - Total Cumulative | E104: Forecast | G104: Total | H104: John / Sheila | I104: 43827 | J104: 43827
A105: 260517 | B105: 46159 | C105: Contracted Lives | D105: Eligible Forecast - Total Cumulative | E105: Forecast | G105: Total | H105: John / Sheila | I105: 50327 | J105: 50327
... A361: 260301 | B361: 46082 | C361: Growth | D361: New Marketable Patients - Same Store | E361: Actual | G361: Same Store | H361: Sheila | I361: 1500 | J361: 1500
A362: 260301 | B362: 46082 | C362: Growth | D362: Total Activations | E362: Forecast | F362: Internal | G362: N/A | H362: Luke | I362: 150 | J362: 150
A363: 260308 | B363: 46089 | C363: Growth | D363: Total Activations | E363: Forecast | F363: Internal | G363: N/A | H363: Luke | I363: 150 | J363: 150
A364: 260315 | B364: 46096 | C364: Growth | D364: Total Activations | E364: Forecast | F364: Internal | G364: N/A | H364: Luke | I364: 150 | J364: 150
A365: 260322 | B365: 46103 | C365: Growth | D365: Total Activations | E365: Forecast | F365: Internal | G365: N/A | H365: Luke | I365: 150 | J365: 150
A366: 260329 | B366: 46110 | C366: Growth | D366: Total Activations | E366: Forecast | F366: Internal | G366: N/A | H366: Luke | I366: 207 | J366: 207
A367: 260405 | B367: 46117 | C367: Growth | D367: Total Activations | E367: Forecast | F367: Internal | G367: N/A | H367: Luke | I367: 245 | J367: 245
A368: 260412 | B368: 46124 | C368: Growth | D368: Total Activations | E368: Forecast | F368: Internal | G368: N/A | H368: Luke | I368: 245 | J368: 245
A369: 260419 | B369: 46131 | C369: Growth | D369: Total Activations | E369: Forecast | F369: Internal | G369: N/A | H369: Luke | I369: 245 | J369: 245
A370: 260426 | B370: 46138 | C370: Growth | D370: Total Activations | E370: Forecast | F370: Internal | G370: N/A | H370: Luke | I370: 269 | J370: 269
A371: 260503 | B371: 46145 | C371: Growth | D371: Total Activations | E371: Forecast | F371: Internal | G371: N/A | H371: Luke | I371: 365 | J371: 365
A372: 260510 | B372: 46152 | C372: Growth | D372: Total Activations | E372: Forecast | F372: Internal | G372: N/A | H372: Luke | I372: 365 | J372: 365
A373: 260517 | B373: 46159 | C373: Growth | D373: Total Activations | E373: Forecast | F373: Internal | G373: N/A | H373: Luke | I373: 365 | J373: 365
... A493: 261227 | B493: 46383 | C493: Growth | D493: Total Activations | E493: Forecast | F493: Projection | G493: N/A | H493: Luke | I493: 244 | J493: 244
A494: 260301 | B494: 46082 | C494: Growth | D494: Total Activations | E494: Actual | G494: N/A | H494: Luke | I494: 155 | J494: 155
A495: 260308 | B495: 46089 | C495: Growth | D495: Total Activations | E495: Actual | G495: N/A | H495: Luke | I495: 160 | J495: 160
A496: 260301 | B496: 46082 | C496: Growth | D496: Total Actives | E496: Goal | F496: Internal | G496: N/A | I496: 8321 | J496: 8321
A497: 260308 | B497: 46089 | C497: Growth | D497: Total Actives | E497: Goal | F497: Internal | G497: N/A | I497: 8396 | J497: 8396
A498: 260315 | B498: 46096 | C498: Growth | D498: Total Actives | E498: Goal | F498: Internal | G498: N/A | I498: 8471 | J498: 8471
A499: 260322 | B499: 46103 | C499: Growth | D499: Total Actives | E499: Goal | F499: Internal | G499: N/A | I499: 8546 | J499: 8546
A500: 260329 | B500: 46110 | C500: Growth | D500: Total Actives | E500: Goal | F500: Internal | G500: N/A | I500: 8681 | J500: 8681
A501: 260405 | B501: 46117 | C501: Growth | D501: Total Actives | E501: Goal | F501: Internal | G501: N/A | I501: 8856 | J501: 8856
A502: 260412 | B502: 46124 | C502: Growth | D502: Total Actives | E502: Goal | F502: Internal | G502: N/A | I502: 9031 | J502: 9031
A503: 260419 | B503: 46131 | C503: Growth | D503: Total Actives | E503: Goal | F503: Internal | G503: N/A | I503: 9206 | J503: 9206
A504: 260426 | B504: 46138 | C504: Growth | D504: Total Actives | E504: Goal | F504: Internal | G504: N/A | I504: 9402 | J504: 9402
A505: 260503 | B505: 46145 | C505: Growth | D505: Total Actives | E505: Goal | F505: Internal | G505: N/A | I505: 9682 | J505: 9682
A506: 260510 | B506: 46152 | C506: Growth | D506: Total Actives | E506: Goal | F506: Internal | G506: N/A | I506: 9962 | J506: 9962
A507: 260517 | B507: 46159 | C507: Growth | D507: Total Actives | E507: Goal | F507: Internal | G507: N/A | I507: 10242 | J507: 10242
... A583: 261227 | B583: 46383 | C583: Growth | D583: Total Actives | E583: Goal | F583: Board | G583: N/A | I583: 19411 | J583: 19411
A584: 260329 | B584: 46110 | C584: Growth | D584: Retention Rate | E584: Goal | G584: N/A | H584: Kit | I584: 0.0375 | J584: 0.0375
A585: 260405 | B585: 46117 | C585: Growth | D585: Retention Rate | E585: Goal | G585: N/A | H585: Kit | I585: 0.0375 | J585: 0.0375
A586: 260412 | B586: 46124 | C586: Growth | D586: Retention Rate | E586: Goal | G586: N/A | H586: Kit | I586: 0.0375 | J586: 0.0375
A587: 260419 | B587: 46131 | C587: Growth | D587: Retention Rate | E587: Goal | G587: N/A | H587: Kit | I587: 0.0375 | J587: 0.0375
A588: 260426 | B588: 46138 | C588: Growth | D588: Retention Rate | E588: Goal | G588: N/A | H588: Kit | I588: 0.0387 | J588: 0.0387
A589: 260503 | B589: 46145 | C589: Growth | D589: Retention Rate | E589: Goal | G589: N/A | H589: Kit | I589: 0.0387 | J589: 0.0387
A590: 260510 | B590: 46152 | C590: Growth | D590: Retention Rate | E590: Goal | G590: N/A | H590: Kit | I590: 0.0387 | J590: 0.0387
A591: 260517 | B591: 46159 | C591: Growth | D591: Retention Rate | E591: Goal | G591: N/A | H591: Kit | I591: 0.0387 | J591: 0.0387
A592: 260524 | B592: 46166 | C592: Growth | D592: Retention Rate | E592: Goal | G592: N/A | H592: Kit | I592: 0.0381 | J592: 0.0381
A593: 260601 | B593: 46174 | C593: Growth | D593: Retention Rate | E593: Goal | G593: N/A | H593: Kit | I593: 0.0381 | J593: 0.0381
A594: 260607 | B594: 46180 | C594: Growth | D594: Retention Rate | E594: Goal | G594: N/A | H594: Kit | I594: 0.0381 | J594: 0.0381
A595: 260614 | B595: 46187 | C595: Growth | D595: Retention Rate | E595: Goal | G595: N/A | H595: Kit | I595: 0.0381 | J595: 0.0381
... A623: 261227 | B623: 46383 | C623: Growth | D623: Retention Rate | E623: Goal | G623: N/A | H623: Kit | I623: 0.0345 | J623: 0.0345
A624: 260301 | B624: 46082 | C624: Growth | D624: Agent Resource Cost Mix (FTE/NS/OS) | E624: Goal | G624: N/A | H624: Luke | I624: 33/67/0%
A625: 260308 | B625: 46089 | C625: Growth | D625: Agent Resource Cost Mix (FTE/NS/OS) | E625: Goal | G625: N/A | H625: Luke | I625: 33/67/0%
A626: 260315 | B626: 46096 | C626: Growth | D626: Agent Resource Cost Mix (FTE/NS/OS) | E626: Goal | G626: N/A | H626: Luke | I626: 33/67/0%
A627: 260322 | B627: 46103 | C627: Growth | D627: Agent Resource Cost Mix (FTE/NS/OS) | E627: Goal | G627: N/A | H627: Luke | I627: 33/67/0%
A628: 260329 | B628: 46110 | C628: Growth | D628: Agent Resource Cost Mix (FTE/NS/OS) | E628: Goal | G628: N/A | H628: Luke | I628: 33/67/0%
A629: 260405 | B629: 46117 | C629: Growth | D629: Agent Resource Cost Mix (FTE/NS/OS) | E629: Goal | G629: N/A | H629: Luke | I629: 18/82/0%
A630: 260412 | B630: 46124 | C630: Growth | D630: Agent Resource Cost Mix (FTE/NS/OS) | E630: Goal | G630: N/A | H630: Luke | I630: 18/82/0%
A631: 260419 | B631: 46131 | C631: Growth | D631: Agent Resource Cost Mix (FTE/NS/OS) | E631: Goal | G631: N/A | H631: Luke | I631: 18/82/0%
A632: 260426 | B632: 46138 | C632: Growth | D632: Agent Resource Cost Mix (FTE/NS/OS) | E632: Goal | G632: N/A | H632: Luke | I632: 18/82/0%
A633: 260503 | B633: 46145 | C633: Growth | D633: Agent Resource Cost Mix (FTE/NS/OS) | E633: Goal | G633: N/A | H633: Luke | I633: 14/67/19%
A634: 260510 | B634: 46152 | C634: Growth | D634: Agent Resource Cost Mix (FTE/NS/OS) | E634: Goal | G634: N/A | H634: Luke | I634: 14/67/19%
A635: 260517 | B635: 46159 | C635: Growth | D635: Agent Resource Cost Mix (FTE/NS/OS) | E635: Goal | G635: N/A | H635: Luke | I635: 14/67/19%
... A667: 261227 | B667: 46383 | C667: Growth | D667: Agent Resource Cost Mix (FTE/NS/OS) | E667: Goal | G667: N/A | H667: Luke | I667: 0/26/74%
A668: 260301 | B668: 46082 | C668: Growth | D668: Enrollment Call Conversions (per rep per hour) | E668: Goal | G668: N/A | H668: Luke | I668: 0.27 | J668: 0.27
A669: 260308 | B669: 46089 | C669: Growth | D669: Enrollment Call Conversions (per rep per hour) | E669: Goal | G669: N/A | H669: Luke | I669: 0.27 | J669: 0.27
A670: 260315 | B670: 46096 | C670: Growth | D670: Enrollment Call Conversions (per rep per hour) | E670: Goal | G670: N/A | H670: Luke | I670: 0.27 | J670: 0.27
A671: 260322 | B671: 46103 | C671: Growth | D671: Enrollment Call Conversions (per rep per hour) | E671: Goal | G671: N/A | H671: Luke | I671: 0.27 | J671: 0.27
A672: 260329 | B672: 46110 | C672: Growth | D672: Enrollment Call Conversions (per rep per hour) | E672: Goal | G672: N/A | H672: Luke | I672: 0.27 | J672: 0.27
A673: 260405 | B673: 46117 | C673: Growth | D673: Enrollment Call Conversions (per rep per hour) | E673: Goal | G673: N/A | H673: Luke | I673: 0.45 | J673: 0.45
A674: 260412 | B674: 46124 | C674: Growth | D674: Enrollment Call Conversions (per rep per hour) | E674: Goal | G674: N/A | H674: Luke | I674: 0.45 | J674: 0.45
A675: 260419 | B675: 46131 | C675: Growth | D675: Enrollment Call Conversions (per rep per hour) | E675: Goal | G675: N/A | H675: Luke | I675: 0.45 | J675: 0.45
A676: 260426 | B676: 46138 | C676: Growth | D676: Enrollment Call Conversions (per rep per hour) | E676: Goal | G676: N/A | H676: Luke | I676: 0.45 | J676: 0.45
A677: 260503 | B677: 46145 | C677: Growth | D677: Enrollment Call Conversions (per rep per hour) | E677: Goal | G677: N/A | H677: Luke | I677: 0.64 | J677: 0.64
A678: 260510 | B678: 46152 | C678: Growth | D678: Enrollment Call Conversions (per rep per hour) | E678: Goal | G678: N/A | H678: Luke | I678: 0.64 | J678: 0.64
A679: 260517 | B679: 46159 | C679: Growth | D679: Enrollment Call Conversions (per rep per hour) | E679: Goal | G679: N/A | H679: Luke | I679: 0.64 | J679: 0.64
... A889: 261227 | B889: 46383 | C889: Care Delivery | D889: Bought Time Billed | E889: Goal | G889: N/A | H889: Alex & Kit | I889: 0.7 | J889: 0.7
A890: 260315 | B890: 46096 | C890: Care Delivery | D890: Care Delivery Time per Care Manager | E890: Goal | G890: N/A | H890: Alex & Kit | I890: March 70%
A891: 260322 | B891: 46103 | C891: Care Delivery | D891: Care Delivery Time per Care Manager | E891: Goal | G891: N/A | H891: Alex & Kit | I891: 0.7 | J891: 0.7
A892: 260329 | B892: 46110 | C892: Care Delivery | D892: Care Delivery Time per Care Manager | E892: Goal | G892: N/A | H892: Alex & Kit | I892: 0.8 | J892: 0.8
A893: 260405 | B893: 46117 | C893: Care Delivery | D893: Care Delivery Time per Care Manager | E893: Goal | G893: N/A | H893: Alex & Kit | I893: 0.8 | J893: 0.8
A894: 260412 | B894: 46124 | C894: Care Delivery | D894: Care Delivery Time per Care Manager | E894: Goal | G894: N/A | H894: Alex & Kit | I894: 0.8 | J894: 0.8
A895: 260419 | B895: 46131 | C895: Care Delivery | D895: Care Delivery Time per Care Manager | E895: Goal | G895: N/A | H895: Alex & Kit | I895: 0.8 | J895: 0.8
...

Sheet fact_initiative_event
A1: date_id | B1: week_start | C1: initiative_id | D1: initiative_name | E1: domain | F1: owner | G1: milestone_text | H1: status_score | I1: status_label | L1: ← Back to Cube Index
A2: 260301 | B2: 46082 | C2: TIE-02 | D2: APCM | E2: Tier 1 Initiative | F2: Team | G2: APCM capability on platform | H2: 0.25 | I2: Early Stage
A3: 260315 | B3: 46096 | C3: TIE-02 | D3: APCM | E3: Tier 1 Initiative | F3: Team | G3: Product training for Sales, PSM, billing (kit) | H3: 0.75 | I3: Near Complete
A4: 260322 | B4: 46103 | C4: TIE-02 | D4: APCM | E4: Tier 1 Initiative | F4: Team | G4: Delivery plan developed for Beney (Sheila) | H4: 0.5 | I4: In Progress
A5: 260412 | B5: 46124 | C5: TIE-02 | D5: APCM | E5: Tier 1 Initiative | F5: Team | G5: Patients identification, rollout plan, dry run-through (sheila, luke) | H5: 0.5 | I5: In Progress
A6: 260419 | B6: 46131 | C6: TIE-02 | D6: APCM | E6: Tier 1 Initiative | F6: Team | G6: First APCM patients on system (Sheila, Luke) | H6: 0.25 | I6: Early Stage
A7: 260426 | B7: 46138 | C7: TIE-02 | D7: APCM | E7: Tier 1 Initiative | F7: Team | G7: APCM Billing readiness. | H7: 0.75 | I7: Near Complete
A8: 260308 | B8: 46089 | C8: TIE-03 | D8: RPM/PCM/CCM Product and onboarding | E8: Tier 1 Initiative | F8: Team | G8: CCM onboarding v0.2 | H8: 0.75 | I8: Near Complete
A9: 260315 | B9: 46096 | C9: TIE-03 | D9: RPM/PCM/CCM Product and onboarding | E9: Tier 1 Initiative | F9: Team | G9: Prod update - 2 conditions | H9: 0.5 | I9: In Progress
A10: 260322 | B10: 46103 | C10: TIE-03 | D10: RPM/PCM/CCM Product and onboarding | E10: Tier 1 Initiative | F10: Team | G10: Change mgt plan for the Intake team (luke) | H10: 0.5 | I10: In Progress
A11: 260412 | B11: 46124 | C11: TIE-03 | D11: RPM/PCM/CCM Product and onboarding | E11: Tier 1 Initiative | F11: Team | G11: CCM onboarding v1.0 | H11: 0.75 | I11: Near Complete
A12: 260301 | B12: 46082 | C12: TIE-04 | D12: Griffin CCM transition and growth | E12: Tier 1 Initiative | F12: Sheila & Luke | G12: Warm transfers started | H12: 0.5 | I12: In Progress
A13: 260315 | B13: 46096 | C13: TIE-04 | D13: Griffin CCM transition and growth | E13: Tier 1 Initiative | F13: Sheila & Luke | G13: Letters sent to Engooden pts. (luke) | H13: 0.75 | I13: Near Complete
... A111: 261206 | B111: 46362 | C111: PEO-06 | D111: HR Calendar | E111: People & Culture | F111: Tricia | G111: Headcount & budget finalized | H111: 1 | I111: Complete

Sheet ref_monthly_narrative
A1: month | B1: year | C1: narrative_text | F1: ← Back to Cube Index
A2: March | B2: 2026 | C2: New activations - 653, total actives EO March - 8,584 1. CCM rollout - 20% of new activations (=130), Griffin as lead, Highgate second 2. RPM 2026 codes - accepted at all accounts (Oren / John / Sheila) 3. Care Efficiency - workforce management - impact (Alex / Kit / Gregg) 4. 3 new contracts need to be signed this month (John) and implementation starting. 5. Completed transition of Highgate from implementation to PSM 6. $0 Copay BI automation 7. CCM onboarding at Griffin + WNY: 100 activations 8. Highgate ramping: 100 activations
A3: April | B3: 2026 | C3: Activations = 1,088. Total actives = 9,348 1. APCM - launched with 1 clinics; X patients (define KPI? Kit/Kelsey) 2. Care Efficiency - impact 3. Brook+ registration conversion improvements - (target 85%) 4. CMN restarted - target if 400 new activation in '26 5. New HS launched - target of 1,500 new patients in '26 - mitigation decision by 3/24/26 6. Griffin CCM transition - goal is to have 850 (200 on RPM currently) Griffin CCM active by end of April. Plan readiness? 7. Comp planning (Gregg/Tricia) 8. 2026 Partner Kick Off 4/20-4/23 9. Engooden patient migration (600 activations) 10. Sturdy opening diagnosis partner rules
A4: May | B4: 2026 | C4: Activations = 1,463. Total actives = 10,462 1. new HS launched - target of 900 new patients in '26 2. new clinic launched - target of 300 new patients in '26 - Need signatures by 3/24/26 3. Patient Retention improvements (SMS nudges)- impact 4. Employee Performance reviews completed??? 5. 3 new partner wins 6. 685 activations forecast to come from new store in May 7. Open (or near open) access to qualified Sturdy patients
A5: June | B5: 2026 | C5: Activations = 1,713. Total actives = 11,784 1. two new clinics launched - target of 1,200 patients in '26 2. Med Mgmt 1st partner contract signed (dependent on revenue convo) 3. By end of June, debt line / financing devices 4. BI. as a service - impact
A6: July | B6: 2026 | C6: Activations = 2,038. Total actives = 13,381 1. Med Management launch, rollout to XX partners 2. new HS launched - target of 1,000 patients in '26 3. Med Mgmt 1st partner launched; Med Mgmt 2nd partner contract signed 4. BI moved to outside vendor 5. Board Retreat
A7: August | B7: 2026 | C7: Activations = 2,228. Total actives = 15,112 1. New clinic launch - target of 600 patients in '26 Med Mgmt 2nd partner launch
A8: September | B8: 2026 | C8: Activations = 2,518. Total actives = 17,074 1. New HS and new Clinic launched - target of 500 new patients in '26.
A9: October | B9: 2026 | C9: Activations = 2,713. Total actives = 19,170 1. new clinic and new HS launch - target of 400 new patients in '26 2.
A10: November | B10: 2026 | C10: Activations = 2,453. Total actives = 20,937 1. new clinic and new HS launch - targeting 150 new patients in '26
A11: December | B11: 2026 | C11: Activations = 2,197. Total actives = 22,407

Sheet enrollment - combined (New)
D2: Start Date | BK2: 46026 | BL2: 46033 | BM2: 46040 | BN2: 46047 | BO2: 46054 | BP2: 46061 | BQ2: 46068 | BR2: 46075 | BS2: 46082 | BT2: 46089 | BU2: 46096 | BV2: 46103 | BW2: 46110 | BX2: 46117 | BY2: 46124 | BZ2: 46131 | CA2: 46138 | CB2: 46145 | CC2: 46152 | CD2: 46159 | CE2: 46166 | CF2: 46173 | CG2: 46180 | CH2: 46187 | CI2: 46194 | CJ2: 46201 | CK2: 46208 | CL2: 46215 | CM2: 46222 | CN2: 46229 | CO2: 46236 | CP2: 46243 | CQ2: 46250 | CR2: 46260 | CS2: 46264 | CT2: 46271 | CU2: 46278 | CV2: 46285 | CW2: 46292 | CX2: 46299 | CY2: 46306 | CZ2: 46313 | DA2: 46320 | DB2: 46327 | DC2: 46334 | DD2: 46341 | DE2: 46348 | DF2: 46355 | DG2: 46362 | DH2: 46369 | DI2: 46376 | DJ2: 46383
BK3: Week 1 | BL3: Week 2 | BM3: Week 3 | BN3: Week 4 | BO3: Week 5 | BP3: Week 6 | BQ3: Week 7 | BR3: Week 8 | BS3: Week 9 | BT3: Week 10 | BU3: Week 11 | BV3: Week 12 | BW3: Week 13 | BX3: Week 14 | BY3: Week 15 | BZ3: Week 16 | CA3: Week 17 | CB3: Week 18 | CC3: Week 19 | CD3: Week 20 | CE3: Week 21 | CF3: Week 22 | CG3: Week 23 | CH3: Week 24 | CI3: Week 25 | CJ3: Week 26 | CK3: Week 27 | CL3: Week 28 | CM3: Week 29 | CN3: Week 30 | CO3: Week 31 | CP3: Week 32 | CQ3: Week 33 | CR3: Week 34 | CS3: Week 35 | CT3: Week 36 | CU3: Week 37 | CV3: Week 38 | CW3: Week 39 | CX3: Week 40 | CY3: Week 41 | CZ3: Week 42 | DA3: Week 43 | DB3: Week 44 | DC3: Week 45 | DD3: Week 46 | DE3: Week 47 | DF3: Week 48 | DG3: Week 49 | DH3: Week 50 | DI3: Week 51 | DJ3: Week 52 | DK3: Total | DL3: check
C5: New Qualfied (John) | BV5: 5000 | BW5: 5000 | BX5: 20000 | BZ5: 10000 | CB5: 20000 | CD5: 10000 | CE5: 5000 | CG5: 20000 | CI5: 5000 | CK5: 40000 | CM5: 5000 | CO5: 10000 | CQ5: 5000 | CS5: 10000 | CT5: 10000 | CV5: 5000 | CW5: 10000 | CY5: 10000 | CZ5: 10000 | DB5: 40000 | DD5: 5000 | DF5: 5000
C6: New Qualified Unlocked (Sheila) | BV6: 3000 | BW6: 2500 | BX6: 10000 | BY6: 5000 | BZ6: 7500 | CA6: 10000 | CB6: 10000 | CC6: 2500 | CD6: 10000 | CE6: 5000 | CF6: 5000 | CG6: 10000 | CH6: 5000 | CI6: 5000 | CJ6: 5000 | CK6: 40000 | CL6: 5000 | CM6: 5000 | CN6: 2500 | CO6: 10000 | CP6: 2500 | CQ6: 2500 | CR6: 5000 | CS6: 5000 | CT6: 1000 | CU6: 2000 | CV6: 5000 | CW6: 10000 | CX6: 2500 | CY6: 2500 | CZ6: 10000 | DA6: 2500 | DB6: 40000 | DC6: 5000 | DD6: 2500 | DE6: 2500 | DF6: 5000 | DG6: 5000 | DH6: 5000 | DI6: 2500 | DJ6: 2500
C7: Locked Qualified | BR7: 10500 | BS7: 21592 | BT7: =BS7+BT5-BT6 -> 21592 | BU7: =BT7+BU5-BU6 -> 21592 | BV7: =BU7+BV5-BV6 -> 23592 | BW7: =BV7+BW5-BW6 -> 26092 | BX7: =BW7+BX5-BX6 -> 36092 | BY7: =BX7+BY5-BY6 -> 31092 | BZ7: =BY7+BZ5-BZ6 -> 33592 | CA7: =BZ7+CA5-CA6 -> 23592 | ... DJ7: =DI7+DJ5-DJ6 -> 8092
C9: Unlock Rate | BR9: 0.4 | BS9: 0.4 | BT9: 0.4 | BU9: 0.4 | BV9: 0.4 | BW9: 0.4 | BX9: 0.4 | BY9: 0.4 | BZ9: 0.4 | CA9: 0.4 | CB9: 0.4 | CC9: 0.4 | CD9: 0.4 | CE9: 0.4 | CF9: 0.4 | CG9: 0.4 | CH9: 0.4 | CI9: 0.4 | CJ9: 0.4 | CK9: 0.4 | CL9: 0.4 | CM9: 0.4 | CN9: 0.4 | CO9: 0.4 | CP9: 0.4 | CQ9: 0.4 | CR9: 0.4 | CS9: 0.4 | CT9: 0.4 | CU9: 0.4 | CV9: 0.4 | CW9: 0.4 | CX9: 0.4 | CY9: 0.4 | CZ9: 0.4 | DA9: 0.4 | DB9: 0.4 | DC9: 0.4 | DD9: 0.4 | DE9: 0.4 | DF9: 0.4 | DG9: 0.4 | DH9: 0.4 | DI9: 0.4 | DJ9: 0.4
C10: Pre-BI Unlocked Eligible | BK10: 11000 | BL10: 11000 | BM10: 11000 | BN10: 11000 | BO10: 11000 | BP10: 11000 | BQ10: 11000 | BR10: 11000 | BS10: =ROUND(BR12+(BS6*BS9),0) -> 9500 | BT10: =ROUND(BS12+(BT6*BT9),0) -> 8000 | BU10: =ROUND(BT12+(BU6*BU9),0) -> 0 | BV10: =ROUND(BU12+(BV6*BV9),0) -> 1200 | BW10: =ROUND(BV12+(BW6*BW9),0) -> 1000 | BX10: =ROUND(BW12+(BX6*BX9),0) -> 4000 | BY10: =ROUND(BX12+(BY6*BY9),0) -> 2000 | BZ10: =ROUND(BY12+(BZ6*BZ9),0) -> 3000 | ... DJ10: =ROUND(DI12+(DJ6*DJ9),0) -> 1000
C11: BI Pace | BK11: 1500 | BL11: 1500 | BM11: 1500 | BN11: 1500 | BO11: 1500 | BP11: 1500 | BQ11: 1500 | BR11: 1500 | BS11: 1500 | BT11: =BT10 -> 8000 | BU11: =BU10 -> 0 | BV11: =BV10 -> 1200 | BW11: =BW10 -> 1000 | BX11: =BX10 -> 4000 | BY11: =BY10 -> 2000 | BZ11: =BZ10 -> 3000 | CA11: =CA10 -> 4000 | ... DJ11: =DJ10 -> 1000
C12: Unlocked Eligible Backlog | BK12: =BK10-BK11 -> 9500 | BL12: =BL10-BL11 -> 9500 | BM12: =BM10-BM11 -> 9500 | BN12: =BN10-BN11 -> 9500 | BO12: =BO10-BO11 -> 9500 | BP12: =BP10-BP11 -> 9500 | BQ12: =BQ10-BQ11 -> 9500 | BR12: =BR10-BR11 -> 9500 | ... DJ12: =DJ10-DJ11 -> 0
C14: Unlock Rate | D14: NEED MARKETABLE RATE OF 80% | BK14: 0.8 | BL14: 0.8 | BM14: 0.8 | BN14: 0.8 | BO14: 0.8 | BP14: 0.8 | BQ14: 0.8 | BR14: 0.8 | BS14: 0.8 | BT14: 0.8 | BU14: 0.8 | BV14: 0.8 | BW14: 0.8 | BX14: 0.8 | BY14: 0.8 | BZ14: 0.8 | CA14: 0.8 | CB14: 0.8 | CC14: 0.8 | CD14: 0.8 | CE14: 0.8 | CF14: 0.8 | CG14: 0.8 | CH14: 0.8 | CI14: 0.8 | CJ14: 0.8 | CK14: 0.8 | CL14: 0.8 | CM14: 0.8 | CN14: 0.8 | CO14: 0.8 | CP14: 0.8 | CQ14: 0.8 | CR14: 0.8 | CS14: 0.8 | CT14: 0.8 | CU14: 0.8 | CV14: 0.8 | CW14: 0.8 | CX14: 0.8 | CY14: 0.8 | CZ14: 0.8 | DA14: 0.8 | DB14: 0.8 | DC14: 0.8 | DD14: 0.8 | DE14: 0.8 | DF14: 0.8 | DG14: 0.8 | DH14: 0.8 | DI14: 0.8 | DJ14: 0.8
C15: New Marketable | BK15: =BK11*BK14 -> 1200 | BL15: =BL11*BL14 -> 1200 | BM15: =BM11*BM14 -> 1200 | BN15: =BN11*BN14 -> 1200 | BO15: =BO11*BO14 -> 1200 | BP15: =BP11*BP14 -> 1200 | BQ15: =BQ11*BQ14 -> 1200 | BR15: =BR11*BR14 -> 1200 | ... DJ15: =DJ11*DJ14 -> 800
C17: Out Of Pocket Band
C18: 0 | D18: 0.35 | BK18: =ROUND(BK$15*$D18,0) -> 420 | BL18: =ROUND(BL$15*$D18,0) -> 420 | BM18: =ROUND(BM$15*$D18,0) -> 420 | BN18: =ROUND(BN$15*$D18,0) -> 420 | BO18: =ROUND(BO$15*$D18,0) -> 420 | BP18: =ROUND(BP$15*$D18,0) -> 420 | BQ18: =ROUND(BQ$15*$D18,0) -> 420 | BR18: =ROUND(BR$15*$D18,0) -> 420 | ... DJ18: =ROUND(DJ$15*$D18,0) -> 280
C19: 1 – 19 | D19: 0.05 | BK19: =ROUND(BK$15*$D19,0) -> 60 | BL19: =ROUND(BL$15*$D19,0) -> 60 | BM19: =ROUND(BM$15*$D19,0) -> 60 | BN19: =ROUND(BN$15*$D19,0) -> 60 | BO19: =ROUND(BO$15*$D19,0) -> 60 | BP19: =ROUND(BP$15*$D19,0) -> 60 | BQ19: =ROUND(BQ$15*$D19,0) -> 60 | BR19: =ROUND(BR$15*$D19,0) -> 60 | ... DJ19: =ROUND(DJ$15*$D19,0) -> 40
C20: 20 – 29 | D20: 0.15 | BK20: =ROUND(BK$15*$D20,0) -> 180 | BL20: =ROUND(BL$15*$D20,0) -> 180 | BM20: =ROUND(BM$15*$D20,0) -> 180 | BN20: =ROUND(BN$15*$D20,0) -> 180 | BO20: =ROUND(BO$15*$D20,0) -> 180 | BP20: =ROUND(BP$15*$D20,0) -> 180 | BQ20: =ROUND(BQ$15*$D20,0) -> 180 | BR20: =ROUND(BR$15*$D20,0) -> 180 | ... DJ20: =ROUND(DJ$15*$D20,0) -> 120
C21: 30 – 39 | D21: 0.05 | BK21: =ROUND(BK$15*$D21,0) -> 60 | BL21: =ROUND(BL$15*$D21,0) -> 60 | BM21: =ROUND(BM$15*$D21,0) -> 60 | BN21: =ROUND(BN$15*$D21,0) -> 60 | BO21: =ROUND(BO$15*$D21,0) -> 60 | BP21: =ROUND(BP$15*$D21,0) -> 60 | BQ21: =ROUND(BQ$15*$D21,0) -> 60 | BR21: =ROUND(BR$15*$D21,0) -> 60 | ... DJ21: =ROUND(DJ$15*$D21,0) -> 40
C22: 40 – 49 | D22: 0.05 | BK22: =ROUND(BK$15*$D22,0) -> 60 | BL22: =ROUND(BL$15*$D22,0) -> 60 | BM22: =ROUND(BM$15*$D22,0) -> 60 | BN22: =ROUND(BN$15*$D22,0) -> 60 | BO22: =ROUND(BO$15*$D22,0) -> 60 | BP22: =ROUND(BP$15*$D22,0) -> 60 | BQ22: =ROUND(BQ$15*$D22,0) -> 60 | BR22: =ROUND(BR$15*$D22,0) -> 60 | ... DJ22: =ROUND(DJ$15*$D22,0) -> 40
C23: 50+ | D23: 0.15 | BK23: =ROUND(BK$15*$D23,0) -> 180 | BL23: =ROUND(BL$15*$D23,0) -> 180 | BM23: =ROUND(BM$15*$D23,0) -> 180 | BN23: =ROUND(BN$15*$D23,0) -> 180 | BO23: =ROUND(BO$15*$D23,0) -> 180 | BP23: =ROUND(BP$15*$D23,0) -> 180 | BQ23: =ROUND(BQ$15*$D23,0) -> 180 | BR23: =ROUND(BR$15*$D23,0) -> 180 | ... DJ23: =ROUND(DJ$15*$D23,0) -> 120
C24: Deductible Remaining | D24: 0.2 | BK24: =ROUND(BK$15*$D24,0) -> 240 | BL24: =ROUND(BL$15*$D24,0) -> 240 | BM24: =ROUND(BM$15*$D24,0) -> 240 | BN24: =ROUND(BN$15*$D24,0) -> 240 | BO24: =ROUND(BO$15*$D24,0) -> 240 | BP24: =ROUND(BP$15*$D24,0) -> 240 | BQ24: =ROUND(BQ$15*$D24,0) -> 240 | BR24: =ROUND(BR$15*$D24,0) -> 240 | ... DJ24: =ROUND(DJ$15*$D24,0) -> 160
C26: Conversion Rate
C27: 0 | D27: 0.35 | BK27: =ROUND(BK18*$D27,0) -> 147 | BL27: =ROUND(BL18*$D27,0) -> 147 | BM27: =ROUND(BM18*$D27,0) -> 147 | BN27: =ROUND(BN18*$D27,0) -> 147 | BO27: =ROUND(BO18*$D27,0) -> 147 | BP27: =ROUND(BP18*$D27,0) -> 147 | BQ27: =ROUND(BQ18*$D27,0) -> 147 | BR27: =ROUND(BR18*$D27,0) -> 147 | ... DJ27: =ROUND(DJ18*$D27,0) -> 98
C28: 1 – 19 | D28: 0.25 | BK28: =ROUND(BK19*$D28,0) -> 15 | BL28: =ROUND(BL19*$D28,0) -> 15 | BM28: =ROUND(BM19*$D28,0) -> 15 | BN28: =ROUND(BN19*$D28,0) -> 15 | BO28: =ROUND(BO19*$D28,0) -> 15 | BP28: =ROUND(BP19*$D28,0) -> 15 | BQ28: =ROUND(BQ19*$D28,0) -> 15 | BR28: =ROUND(BR19*$D28,0) -> 15 | ... DJ28: =ROUND(DJ19*$D28,0) -> 10
C29: 20 – 29 | D29: 0.15 | BK29: =ROUND(BK20*$D29,0) -> 27 | BL29: =ROUND(BL20*$D29,0) -> 27 | BM29: =ROUND(BM20*$D29,0) -> 27 | BN29: =ROUND(BN20*$D29,0) -> 27 | BO29: =ROUND(BO20*$D29,0) -> 27 | BP29: =ROUND(BP20*$D29,0) -> 27 | BQ29: =ROUND(BQ20*$D29,0) -> 27 | BR29: =ROUND(BR20*$D29,0) -> 27 | ... DJ29: =ROUND(DJ20*$D29,0) -> 18
C30: 30 – 39 | D30: 0.09 | BK30: =ROUND(BK21*$D30,0) -> 5 | BL30: =ROUND(BL21*$D30,0) -> 5 | BM30: =ROUND(BM21*$D30,0) -> 5 | BN30: =ROUND(BN21*$D30,0) -> 5 | BO30: =ROUND(BO21*$D30,0) -> 5 | BP30: =ROUND(BP21*$D30,0) -> 5 | BQ30: =ROUND(BQ21*$D30,0) -> 5 | BR30: =ROUND(BR21*$D30,0) -> 5 | ... DJ30: =ROUND(DJ21*$D30,0) -> 4
C31: 40 – 49 | D31: 0.07 | BK31: =ROUND(BK22*$D31,0) -> 4 | BL31: =ROUND(BL22*$D31,0) -> 4 | BM31: =ROUND(BM22*$D31,0) -> 4 | BN31: =ROUND(BN22*$D31,0) -> 4 | BO31: =ROUND(BO22*$D31,0) -> 4 | BP31: =ROUND(BP22*$D31,0) -> 4 | BQ31: =ROUND(BQ22*$D31,0) -> 4 | BR31: =ROUND(BR22*$D31,0) -> 4 | ... DJ31: =ROUND(DJ22*$D31,0) -> 3
C32: 50+ | D32: 0.05 | BK32: =ROUND(BK23*$D32,0) -> 9 | BL32: =ROUND(BL23*$D32,0) -> 9 | BM32: =ROUND(BM23*$D32,0) -> 9 | BN32: =ROUND(BN23*$D32,0) -> 9 | BO32: =ROUND(BO23*$D32,0) -> 9 | BP32: =ROUND(BP23*$D32,0) -> 9 | BQ32: =ROUND(BQ23*$D32,0) -> 9 | BR32: =ROUND(BR23*$D32,0) -> 9 | ... DJ32: =ROUND(DJ23*$D32,0) -> 6
C33: Deductible Remaining | D33: 0.05 | BK33: =ROUND(BK24*$D33,0) -> 12 | BL33: =ROUND(BL24*$D33,0) -> 12 | BM33: =ROUND(BM24*$D33,0) -> 12 | BN33: =ROUND(BN24*$D33,0) -> 12 | BO33: =ROUND(BO24*$D33,0) -> 12 | BP33: =ROUND(BP24*$D33,0) -> 12 | BQ33: =ROUND(BQ24*$D33,0) -> 12 | BR33: =ROUND(BR24*$D33,0) -> 12 | ... DJ33: =ROUND(DJ24*$D33,0) -> 8
C35: Conversion Pace
B36: Week | C36: 1 | D36: 0 | E36: 0.07 | F36: 0.07 | G36: 0.07 | H36: 0.07 | I36: 0.07 | J36: 0.07 | K36: 0.07 | L36: 0.07 | M36: 0.07 | N36: 0.03 | O36: 0.03 | P36: 0.03 | Q36: 0.03 | R36: 0.03 | S36: 0.03 | T36: 0.03 | U36: 0.02 | V36: 0.02 | W36: 0.02 | X36: 0.02 | Y36: 0.02 | Z36: 0.02 | AA36: 0.02 | AB36: 0.02 | BK36: =ROUND($BK27*E36,0) -> 10 | BL36: =ROUND($BK27*F36,0) -> 10 | BM36: =ROUND($BK27*G36,0) -> 10 | BN36: =ROUND($BK27*H36,0) -> 10 | BO36: =ROUND($BK27*I36,0) -> 10 | BP36: =ROUND($BK27*J36,0) -> 10 | BQ36: =ROUND($BK27*K36,0) -> 10 | BR36: =ROUND($BK27*L36,0) -> 10 | ... DJ36: =ROUND($BK27*BD36,0) -> 0
B37: Week | C37: 1 | D37: 1 – 19 | E37: 0.02 | F37: 0.02 | G37: 0.02 | H37: 0.02 | I37: 0.08 | J37: 0.08 | K37: 0.07 | L37: 0.07 | M37: 0.06 | N37: 0.06 | O37: 0.05 | P37: 0.05 | Q37: 0.05 | R37: 0.04 | S37: 0.04 | T37: 0.04 | U37: 0.04 | V37: 0.03 | W37: 0.03 | X37: 0.03 | Y37: 0.03 | Z37: 0.03 | AA37: 0.02 | AB37: 0.02 | BK37: =ROUND($BK28*E37,0) -> 0 | BL37: =ROUND($BK28*F37,0) -> 0 | BM37: =ROUND($BK28*G37,0) -> 0 | BN37: =ROUND($BK28*H37,0) -> 0 | BO37: =ROUND($BK28*I37,0) -> 1 | BP37: =ROUND($BK28*J37,0) -> 1 | BQ37: =ROUND($BK28*K37,0) -> 1 | BR37: =ROUND($BK28*L37,0) -> 1 | ... DJ37: =ROUND($BK28*BD37,0) -> 0
B38: Week | C38: 1 | D38: 20 – 29 | H38: 0.08 | I38: 0.08 | J38: 0.07 | K38: 0.07 | L38: 0.06 | M38: 0.06 | N38: 0.05 | O38: 0.05 | P38: 0.05 | Q38: 0.04 | R38: 0.04 | S38: 0.04 | T38: 0.04 | U38: 0.03 | V38: 0.03 | W38: 0.03 | X38: 0.03 | Y38: 0.03 | Z38: 0.02 | AA38: 0.02 | AB38: 0.03 | AC38: 0.03 | AD38: 0.02 | BK38: =ROUND($BK29*E38,0) -> 0 | BL38: =ROUND($BK29*F38,0) -> 0 | BM38: =ROUND($BK29*G38,0) -> 0 | BN38: =ROUND($BK29*H38,0) -> 2 | BO38: =ROUND($BK29*I38,0) -> 2 | BP38: =ROUND($BK29*J38,0) -> 2 | BQ38: =ROUND($BK29*K38,0) -> 2 | BR38: =ROUND($BK29*L38,0) -> 2 | ... DJ38: =ROUND($BK29*BD38,0) -> 0
B39: Week | C39: 1 | D39: 30 – 39 | J39: 0.08 | K39: 0.08 | L39: 0.07 | M39: 0.07 | N39: 0.06 | O39: 0.06 | P39: 0.05 | Q39: 0.05 | R39: 0.05 | S39: 0.04 | T39: 0.04 | U39: 0.04 | V39: 0.04 | W39: 0.03 | X39: 0.03 | Y39: 0.03 | Z39: 0.03 | AA39: 0.03 | AB39: 0.02 | AC39: 0.02 | AD39: 0.03 | BK39: =ROUND($BK30*E39,0) -> 0 | BL39: =ROUND($BK30*F39,0) -> 0 | BM39: =ROUND($BK30*G39,0) -> 0 | BN39: =ROUND($BK30*H39,0) -> 0 | BO39: =ROUND($BK30*I39,0) -> 0 | BP39: =ROUND($BK30*J39,0) -> 0 | BQ39: =ROUND($BK30*K39,0) -> 0 | BR39: =ROUND($BK30*L39,0) -> 0 | ... DJ39: =ROUND($BK30*BD39,0) -> 0
B40: Week | C40: 1 | D40: 40 – 49 | K40: 0.08 | L40: 0.08 | M40: 0.07 | N40: 0.07 | O40: 0.06 | P40: 0.06 | Q40: 0.05 | R40: 0.05 | S40: 0.05 | T40: 0.04 | U40: 0.04 | V40: 0.04 | W40: 0.04 | X40: 0.03 | Y40: 0.03 | Z40: 0.03 | AA40: 0.03 | AB40: 0.03 | AC40: 0.02 | AD40: 0.02 | BK40: =ROUND($BK31*E40,0) -> 0 | BL40: =ROUND($BK31*F40,0) -> 0 | BM40: =ROUND($BK31*G40,0) -> 0 | BN40: =ROUND($BK31*H40,0) -> 0 | BO40: =ROUND($BK31*I40,0) -> 0 | BP40: =ROUND($BK31*J40,0) -> 0 | BQ40: =ROUND($BK31*K40,0) -> 0 | BR40: =ROUND($BK31*L40,0) -> 0 | ... DJ40: =ROUND($BK31*BD40,0) -> 0
B41: Week | C41: 1 | D41: 50+ | L41: 0.08 | M41: 0.08 | N41: 0.07 | O41: 0.07 | P41: 0.06 | Q41: 0.06 | R41: 0.05 | S41: 0.05 | T41: 0.05 | U41: 0.04 | V41: 0.04 | W41: 0.04 | X41: 0.04 | Y41: 0.03 | Z41: 0.03 | AA41: 0.03 | AB41: 0.03 | AC41: 0.03 | AD41: 0.02 | BK41: =ROUND($BK32*E41,0) -> 0 | BL41: =ROUND($BK32*F41,0) -> 0 | BM41: =ROUND($BK32*G41,0) -> 0 | BN41: =ROUND($BK32*H41,0) -> 0 | BO41: =ROUND($BK32*I41,0) -> 0 | BP41: =ROUND($BK32*J41,0) -> 0 | BQ41: =ROUND($BK32*K41,0) -> 0 | BR41: =ROUND($BK32*L41,0) -> 1 | ... DJ41: =ROUND($BK32*BD41,0) -> 0
B42: Week | C42: 1 | D42: Deductible Remaining | N42: 0.08 | O42: 0.08 | P42: 0.07 | Q42: 0.07 | R42: 0.06 | S42: 0.06 | T42: 0.05 | U42: 0.05 | V42: 0.05 | W42: 0.04 | X42: 0.04 | Y42: 0.04 | Z42: 0.04 | AA42: 0.03 | AB42: 0.03 | AC42: 0.03 | AD42: 0.03 | BK42: =ROUND($BK33*E42,0) -> 0 | BL42: =ROUND($BK33*F42,0) -> 0 | BM42: =ROUND($BK33*G42,0) -> 0 | BN42: =ROUND($BK33*H42,0) -> 0 | BO42: =ROUND($BK33*I42,0) -> 0 | BP42: =ROUND($BK33*J42,0) -> 0 | BQ42: =ROUND($BK33*K42,0) -> 0 | BR42: =ROUND($BK33*L42,0) -> 0 | ... DJ42: =ROUND($BK33*BD42,0) -> 0
B43: Week | C43: 2 | D43: 0 | E43: 0.07 | F43: 0.07 | G43: 0.07 | H43: 0.07 | I43: 0.07 | J43: 0.07 | K43: 0.07 | L43: 0.07 | M43: 0.07 | N43: 0.03 | O43: 0.03 | P43: 0.03 | Q43: 0.03 | R43: 0.03 | S43: 0.03 | T43: 0.03 | U43: 0.02 | V43: 0.02 | W43: 0.02 | X43: 0.02 | Y43: 0.02 | Z43: 0.02 | AA43: 0.02 | AB43: 0.02 | BL43: =ROUND($BL27*E43,0) -> 10 | BM43: =ROUND($BL27*F43,0) -> 10 | BN43: =ROUND($BL27*G43,0) -> 10 | BO43: =ROUND($BL27*H43,0) -> 10 | BP43: =ROUND($BL27*I43,0) -> 10 | BQ43: =ROUND($BL27*J43,0) -> 10 | BR43: =ROUND($BL27*K43,0) -> 10 | BS43: =ROUND($BL27*L43,0) -> 10 | ... DJ43: =ROUND($BL27*BC43,0) -> 0
B44: Week | C44: 2 | D44: 1 – 19 | E44: 0.02 | F44: 0.02 | G44: 0.02 | H44: 0.02 | I44: 0.08 | J44: 0.08 | K44: 0.07 | L44: 0.07 | M44: 0.06 | N44: 0.06 | O44: 0.05 | P44: 0.05 | Q44: 0.05 | R44: 0.04 | S44: 0.04 | T44: 0.04 | U44: 0.04 | V44: 0.03 | W44: 0.03 | X44: 0.03 | Y44: 0.03 | Z44: 0.03 | AA44: 0.02 | AB44: 0.02 | BL44: =ROUND($BL28*E44,0) -> 0 | BM44: =ROUND($BL28*F44,0) -> 0 | BN44: =ROUND($BL28*G44,0) -> 0 | BO44: =ROUND($BL28*H44,0) -> 0 | BP44: =ROUND($BL28*I44,0) -> 1 | BQ44: =ROUND($BL28*J44,0) -> 1 | BR44: =ROUND($BL28*K44,0) -> 1 | BS44: =ROUND($BL28*L44,0) -> 1 | ... DJ44: =ROUND($BL28*BC44,0) -> 0
B45: Week | C45: 2 | D45: 20 – 29 | H45: 0.08 | I45: 0.08 | J45: 0.07 | K45: 0.07 | L45: 0.06 | M45: 0.06 | N45: 0.05 | O45: 0.05 | P45: 0.05 | Q45: 0.04 | R45: 0.04 | S45: 0.04 | T45: 0.04 | U45: 0.03 | V45: 0.03 | W45: 0.03 | X45: 0.03 | Y45: 0.03 | Z45: 0.02 | AA45: 0.02 | AB45: 0.03 | AC45: 0.03 | AD45: 0.02 | BL45: =ROUND($BL29*E45,0) -> 0 | BM45: =ROUND($BL29*F45,0) -> 0 | BN45: =ROUND($BL29*G45,0) -> 0 | BO45: =ROUND($BL29*H45,0) -> 2 | BP45: =ROUND($BL29*I45,0) -> 2 | BQ45: =ROUND($BL29*J45,0) -> 2 | BR45: =ROUND($BL29*K45,0) -> 2 | BS45: =ROUND($BL29*L45,0) -> 2 | ... DJ45: =ROUND($BL29*BC45,0) -> 0
B46: Week | C46: 2 | D46: 30 – 39 | J46: 0.08 | K46: 0.08 | L46: 0.07 | M46: 0.07 | N46: 0.06 | O46: 0.06 | P46: 0.05 | Q46: 0.05 | R46: 0.05 | S46: 0.04 | T46: 0.04 | U46: 0.04 | V46: 0.04 | W46: 0.03 | X46: 0.03 | Y46: 0.03 | Z46: 0.03 | AA46: 0.03 | AB46: 0.02 | AC46: 0.02 | AD46: 0.03 | BL46: =ROUND($BL30*E46,0) -> 0 | BM46: =ROUND($BL30*F46,0) -> 0 | BN46: =ROUND($BL30*G46,0) -> 0 | BO46: =ROUND($BL30*H46,0) -> 0 | BP46: =ROUND($BL30*I46,0) -> 0 | BQ46: =ROUND($BL30*J46,0) -> 0 | BR46: =ROUND($BL30*K46,0) -> 0 | BS46: =ROUND($BL30*L46,0) -> 0 | ... DJ46: =ROUND($BL30*BC46,0) -> 0
B47: Week | C47: 2 | D47: 40 – 49 | K47: 0.08 | L47: 0.08 | M47: 0.07 | N47: 0.07 | O47: 0.06 | P47: 0.06 | Q47: 0.05 | R47: 0.05 | S47: 0.05 | T47: 0.04 | U47: 0.04 | V47: 0.04 | W47: 0.04 | X47: 0.03 | Y47: 0.03 | Z47: 0.03 | AA47: 0.03 | AB47: 0.03 | AC47: 0.02 | AD47: 0.02 | BL47: =ROUND($BL31*E47,0) -> 0 | BM47: =ROUND($BL31*F47,0) -> 0 | BN47: =ROUND($BL31*G47,0) -> 0 | BO47: =ROUND($BL31*H47,0) -> 0 | BP47: =ROUND($BL31*I47,0) -> 0 | BQ47: =ROUND($BL31*J47,0) -> 0 | BR47: =ROUND($BL31*K47,0) -> 0 | BS47: =ROUND($BL31*L47,0) -> 0 | ... DJ47: =ROUND($BL31*BC47,0) -> 0
B48: Week | C48: 2 | D48: 50+ | L48: 0.08 | M48: 0.08 | N48: 0.07 | O48: 0.07 | P48: 0.06 | Q48: 0.06 | R48: 0.05 | S48: 0.05 | T48: 0.05 | U48: 0.04 | V48: 0.04 | W48: 0.04 | X48: 0.04 | Y48: 0.03 | Z48: 0.03 | AA48: 0.03 | AB48: 0.03 | AC48: 0.03 | AD48: 0.02 | BL48: =ROUND($BL32*E48,0) -> 0 | BM48: =ROUND($BL32*F48,0) -> 0 | BN48: =ROUND($BL32*G48,0) -> 0 | BO48: =ROUND($BL32*H48,0) -> 0 | BP48: =ROUND($BL32*I48,0) -> 0 | BQ48: =ROUND($BL32*J48,0) -> 0 | BR48: =ROUND($BL32*K48,0) -> 0 | BS48: =ROUND($BL32*L48,0) -> 1 | ... DJ48: =ROUND($BL32*BC48,0) -> 0
B49: Week | C49: 2 | D49: Deductible Remaining | N49: 0.08 | O49: 0.08 | P49: 0.07 | Q49: 0.07 | R49: 0.06 | S49: 0.06 | T49: 0.05 | U49: 0.05 | V49: 0.05 | W49: 0.04 | X49: 0.04 | Y49: 0.04 | Z49: 0.04 | AA49: 0.03 | AB49: 0.03 | AC49: 0.03 | AD49: 0.03 | BL49: =ROUND($BL33*E49,0) -> 0 | BM49: =ROUND($BL33*F49,0) -> 0 | BN49: =ROUND($BL33*G49,0) -> 0 | BO49: =ROUND($BL33*H49,0) -> 0 | BP49: =ROUND($BL33*I49,0) -> 0 | BQ49: =ROUND($BL33*J49,0) -> 0 | BR49: =ROUND($BL33*K49,0) -> 0 | BS49: =ROUND($BL33*L49,0) -> 0 | ... DJ49: =ROUND($BL33*BC49,0) -> 0
B50: Week | C50: 3 | D50: 0 | E50: 0.07 | F50: 0.07 | G50: 0.07 | H50: 0.07 | I50: 0.07 | J50: 0.07 | K50: 0.07 | L50: 0.07 | M50: 0.07 | N50: 0.03 | O50: 0.03 | P50: 0.03 | Q50: 0.03 | R50: 0.03 | S50: 0.03 | T50: 0.03 | U50: 0.02 | V50: 0.02 | W50: 0.02 | X50: 0.02 | Y50: 0.02 | Z50: 0.02 | AA50: 0.02 | AB50: 0.02 | BM50: =ROUND($BM27*E50,0) -> 10 | BN50: =ROUND($BM27*F50,0) -> 10 | BO50: =ROUND($BM27*G50,0) -> 10 | BP50: =ROUND($BM27*H50,0) -> 10 | BQ50: =ROUND($BM27*I50,0) -> 10 | BR50: =ROUND($BM27*J50,0) -> 10 | BS50: =ROUND($BM27*K50,0) -> 10 | BT50: =ROUND($BM27*L50,0) -> 10 | ... DJ50: =ROUND($BM27*BB50,0) -> 0
B51: Week | C51: 3 | D51: 1 – 19 | E51: 0.02 | F51: 0.02 | G51: 0.02 | H51: 0.02 | I51: 0.08 | J51: 0.08 | K51: 0.07 | L51: 0.07 | M51: 0.06 | N51: 0.06 | O51: 0.05 | P51: 0.05 | Q51: 0.05 | R51: 0.04 | S51: 0.04 | T51: 0.04 | U51: 0.04 | V51: 0.03 | W51: 0.03 | X51: 0.03 | Y51: 0.03 | Z51: 0.03 | AA51: 0.02 | AB51: 0.02 | BM51: =ROUND($BM28*E51,0) -> 0 | BN51: =ROUND($BM28*F51,0) -> 0 | BO51: =ROUND($BM28*G51,0) -> 0 | BP51: =ROUND($BM28*H51,0) -> 0 | BQ51: =ROUND($BM28*I51,0) -> 1 | BR51: =ROUND($BM28*J51,0) -> 1 | BS51: =ROUND($BM28*K51,0) -> 1 | BT51: =ROUND($BM28*L51,0) -> 1 | ... DJ51: =ROUND($BM28*BB51,0) -> 0
B52: Week | C52: 3 | D52: 20 – 29 | H52: 0.08 | I52: 0.08 | J52: 0.07 | K52: 0.07 | L52: 0.06 | M52: 0.06 | N52: 0.05 | O52: 0.05 | P52: 0.05 | Q52: 0.04 | R52: 0.04 | S52: 0.04 | T52: 0.04 | U52: 0.03 | V52: 0.03 | W52: 0.03 | X52: 0.03 | Y52: 0.03 | Z52: 0.02 | AA52: 0.02 | AB52: 0.03 | AC52: 0.03 | AD52: 0.02 | BM52: =ROUND($BM29*E52,0) -> 0 | BN52: =ROUND($BM29*F52,0) -> 0 | BO52: =ROUND($BM29*G52,0) -> 0 | BP52: =ROUND($BM29*H52,0) -> 2 | BQ52: =ROUND($BM29*I52,0) -> 2 | BR52: =ROUND($BM29*J52,0) -> 2 | BS52: =ROUND($BM29*K52,0) -> 2 | BT52: =ROUND($BM29*L52,0) -> 2 | ... DJ52: =ROUND($BM29*BB52,0) -> 0
B53: Week | C53: 3 | D53: 30 – 39 | J53: 0.08 | K53: 0.08 | L53: 0.07 | M53: 0.07 | N53: 0.06 | O53: 0.06 | P53: 0.05 | Q53: 0.05 | R53: 0.05 | S53: 0.04 | T53: 0.04 | U53: 0.04 | V53: 0.04 | W53: 0.03 | X53: 0.03 | Y53: 0.03 | Z53: 0.03 | AA53: 0.03 | AB53: 0.02 | AC53: 0.02 | AD53: 0.03 | BM53: =ROUND($BM30*E53,0) -> 0 | BN53: =ROUND($BM30*F53,0) -> 0 | BO53: =ROUND($BM30*G53,0) -> 0 | BP53: =ROUND($BM30*H53,0) -> 0 | BQ53: =ROUND($BM30*I53,0) -> 0 | BR53: =ROUND($BM30*J53,0) -> 0 | BS53: =ROUND($BM30*K53,0) -> 0 | BT53: =ROUND($BM30*L53,0) -> 0 | ... DJ53: =ROUND($BM30*BB53,0) -> 0
B54: Week | C54: 3 | D54: 40 – 49 | K54: 0.08 | L54: 0.08 | M54: 0.07 | N54: 0.07 | O54: 0.06 | P54: 0.06 | Q54: 0.05 | R54: 0.05 | S54: 0.05 | T54: 0.04 | U54: 0.04 | V54: 0.04 | W54: 0.04 | X54: 0.03 | Y54: 0.03 | Z54: 0.03 | AA54: 0.03 | AB54: 0.03 | AC54: 0.02 | AD54: 0.02 | BM54: =ROUND($BM31*E54,0) -> 0 | BN54: =ROUND($BM31*F54,0) -> 0 | BO54: =ROUND($BM31*G54,0) -> 0 | BP54: =ROUND($BM31*H54,0) -> 0 | BQ54: =ROUND($BM31*I54,0) -> 0 | BR54: =ROUND($BM31*J54,0) -> 0 | BS54: =ROUND($BM31*K54,0) -> 0 | BT54: =ROUND($BM31*L54,0) -> 0 | ... DJ54: =ROUND($BM31*BB54,0) -> 0
B55: Week | C55: 3 | D55: 50+ | L55: 0.08 | M55: 0.08 | N55: 0.07 | O55: 0.07 | P55: 0.06 | Q55: 0.06 | R55: 0.05 | S55: 0.05 | T55: 0.05 | U55: 0.04 | V55: 0.04 | W55: 0.04 | X55: 0.04 | Y55: 0.03 | Z55: 0.03 | AA55: 0.03 | AB55: 0.03 | AC55: 0.03 | AD55: 0.02 | BM55: =ROUND($BM32*E55,0) -> 0 | BN55: =ROUND($BM32*F55,0) -> 0 | BO55: =ROUND($BM32*G55,0) -> 0 | BP55: =ROUND($BM32*H55,0) -> 0 | BQ55: =ROUND($BM32*I55,0) -> 0 | BR55: =ROUND($BM32*J55,0) -> 0 | BS55: =ROUND($BM32*K55,0) -> 0 | BT55: =ROUND($BM32*L55,0) -> 1 | ... DJ55: =ROUND($BM32*BB55,0) -> 0
B56: Week | C56: 3 | D56: Deductible Remaining | N56: 0.08 | O56: 0.08 | P56: 0.07 | Q56: 0.07 | R56: 0.06 | S56: 0.06 | T56: 0.05 | U56: 0.05 | V56: 0.05 | W56: 0.04 | X56: 0.04 | Y56: 0.04 | Z56: 0.04 | AA56: 0.03 | AB56: 0.03 | AC56: 0.03 | AD56: 0.03 | BM56: =ROUND($BM33*E56,0) -> 0 | BN56: =ROUND($BM33*F56,0) -> 0 | BO56: =ROUND($BM33*G56,0) -> 0 | BP56: =ROUND($BM33*H56,0) -> 0 | BQ56: =ROUND($BM33*I56,0) -> 0 | BR56: =ROUND($BM33*J56,0) -> 0 | BS56: =ROUND($BM33*K56,0) -> 0 | BT56: =ROUND($BM33*L56,0) -> 0 | ... DJ56: =ROUND($BM33*BB56,0) -> 0
B57: Week | C57: 4 | D57: 0 | E57: 0.07 | F57: 0.07 | G57: 0.07 | H57: 0.07 | I57: 0.07 | J57: 0.07 | K57: 0.07 | L57: 0.07 | M57: 0.07 | N57: 0.03 | O57: 0.03 | P57: 0.03 | Q57: 0.03 | R57: 0.03 | S57: 0.03 | T57: 0.03 | U57: 0.02 | V57: 0.02 | W57: 0.02 | X57: 0.02 | Y57: 0.02 | Z57: 0.02 | AA57: 0.02 | AB57: 0.02 | BN57: =ROUND($BN27*E57,0) -> 10 | BO57: =ROUND($BN27*F57,0) -> 10 | BP57: =ROUND($BN27*G57,0) -> 10 | BQ57: =ROUND($BN27*H57,0) -> 10 | BR57: =ROUND($BN27*I57,0) -> 10 | BS57: =ROUND($BN27*J57,0) -> 10 | BT57: =ROUND($BN27*K57,0) -> 10 | BU57: =ROUND($BN27*L57,0) -> 10 | ... DJ57: =ROUND($BN27*BA57,0) -> 0
B58: Week | C58: 4 | D58: 1 – 19 | E58: 0.02 | F58: 0.02 | G58: 0.02 | H58: 0.02 | I58: 0.08 | J58: 0.08 | K58: 0.07 | L58: 0.07 | M58: 0.06 | N58: 0.06 | O58: 0.05 | P58: 0.05 | Q58: 0.05 | R58: 0.04 | S58: 0.04 | T58: 0.04 | U58: 0.04 | V58: 0.03 | W58: 0.03 | X58: 0.03 | Y58: 0.03 | Z58: 0.03 | AA58: 0.02 | AB58: 0.02 | BN58: =ROUND($BN28*E58,0) -> 0 | BO58: =ROUND($BN28*F58,0) -> 0 | BP58: =ROUND($BN28*G58,0) -> 0 | BQ58: =ROUND($BN28*H58,0) -> 0 | BR58: =ROUND($BN28*I58,0) -> 1 | BS58: =ROUND($BN28*J58,0) -> 1 | BT58: =ROUND($BN28*K58,0) -> 1 | BU58: =ROUND($BN28*L58,0) -> 1 | ... DJ58: =ROUND($BN28*BA58,0) -> 0
B59: Week | C59: 4 | D59: 20 – 29 | H59: 0.08 | I59: 0.08 | J59: 0.07 | K59: 0.07 | L59: 0.06 | M59: 0.06 | N59: 0.05 | O59: 0.05 | P59: 0.05 | Q59: 0.04 | R59: 0.04 | S59: 0.04 | T59: 0.04 | U59: 0.03 | V59: 0.03 | W59: 0.03 | X59: 0.03 | Y59: 0.03 | Z59: 0.02 | AA59: 0.02 | AB59: 0.03 | AC59: 0.03 | AD59: 0.02 | BN59: =ROUND($BN29*E59,0) -> 0 | BO59: =ROUND($BN29*F59,0) -> 0 | BP59: =ROUND($BN29*G59,0) -> 0 | BQ59: =ROUND($BN29*H59,0) -> 2 | BR59: =ROUND($BN29*I59,0) -> 2 | BS59: =ROUND($BN29*J59,0) -> 2 | BT59: =ROUND($BN29*K59,0) -> 2 | BU59: =ROUND($BN29*L59,0) -> 2 | ... DJ59: =ROUND($BN29*BA59,0) -> 0
B60: Week | C60: 4 | D60: 30 – 39 | J60: 0.08 | K60: 0.08 | L60: 0.07 | M60: 0.07 | N60: 0.06 | O60: 0.06 | P60: 0.05 | Q60: 0.05 | R60: 0.05 | S60: 0.04 | T60: 0.04 | U60: 0.04 | V60: 0.04 | W60: 0.03 | X60: 0.03 | Y60: 0.03 | Z60: 0.03 | AA60: 0.03 | AB60: 0.02 | AC60: 0.02 | AD60: 0.03 | BN60: =ROUND($BN30*E60,0) -> 0 | BO60: =ROUND($BN30*F60,0) -> 0 | BP60: =ROUND($BN30*G60,0) -> 0 | BQ60: =ROUND($BN30*H60,0) -> 0 | BR60: =ROUND($BN30*I60,0) -> 0 | BS60: =ROUND($BN30*J60,0) -> 0 | BT60: =ROUND($BN30*K60,0) -> 0 | BU60: =ROUND($BN30*L60,0) -> 0 | ... DJ60: =ROUND($BN30*BA60,0) -> 0
B61: Week | C61: 4 | D61: 40 – 49 | K61: 0.08 | L61: 0.08 | M61: 0.07 | N61: 0.07 | O61: 0.06 | P61: 0.06 | Q61: 0.05 | R61: 0.05 | S61: 0.05 | T61: 0.04 | U61: 0.04 | V61: 0.04 | W61: 0.04 | X61: 0.03 | Y61: 0.03 | Z61: 0.03 | AA61: 0.03 | AB61: 0.03 | AC61: 0.02 | AD61: 0.02 | BN61: =ROUND($BN31*E61,0) -> 0 | BO61: =ROUND($BN31*F61,0) -> 0 | BP61: =ROUND($BN31*G61,0) -> 0 | BQ61: =ROUND($BN31*H61,0) -> 0 | BR61: =ROUND($BN31*I61,0) -> 0 | BS61: =ROUND($BN31*J61,0) -> 0 | BT61: =ROUND($BN31*K61,0) -> 0 | BU61: =ROUND($BN31*L61,0) -> 0 | ... DJ61: =ROUND($BN31*BA61,0) -> 0
B62: Week | C62: 4 | D62: 50+ | L62: 0.08 | M62: 0.08 | N62: 0.07 | O62: 0.07 | P62: 0.06 | Q62: 0.06 | R62: 0.05 | S62: 0.05 | T62: 0.05 | U62: 0.04 | V62: 0.04 | W62: 0.04 | X62: 0.04 | Y62: 0.03 | Z62: 0.03 | AA62: 0.03 | AB62: 0.03 | AC62: 0.03 | AD62: 0.02 | BN62: =ROUND($BN32*E62,0) -> 0 | BO62: =ROUND($BN32*F62,0) -> 0 | BP62: =ROUND($BN32*G62,0) -> 0 | BQ62: =ROUND($BN32*H62,0) -> 0 | BR62: =ROUND($BN32*I62,0) -> 0 | BS62: =ROUND($BN32*J62,0) -> 0 | BT62: =ROUND($BN32*K62,0) -> 0 | BU62: =ROUND($BN32*L62,0) -> 1 | ... DJ62: =ROUND($BN32*BA62,0) -> 0
B63: Week | C63: 4 | D63: Deductible Remaining | N63: 0.08 | O63: 0.08 | P63: 0.07 | Q63: 0.07 | R63: 0.06 | S63: 0.06 | T63: 0.05 | U63: 0.05 | V63: 0.05 | W63: 0.04 | X63: 0.04 | Y63: 0.04 | Z63: 0.04 | AA63: 0.03 | AB63: 0.03 | AC63: 0.03 | AD63: 0.03 | BN63: =ROUND($BN33*E63,0) -> 0 | BO63: =ROUND($BN33*F63,0) -> 0 | BP63: =ROUND($BN33*G63,0) -> 0 | BQ63: =ROUND($BN33*H63,0) -> 0 | BR63: =ROUND($BN33*I63,0) -> 0 | BS63: =ROUND($BN33*J63,0) -> 0 | BT63: =ROUND($BN33*K63,0) -> 0 | BU63: =ROUND($BN33*L63,0) -> 0 | ... DJ63: =ROUND($BN33*BA63,0) -> 0
B64: Week | C64: 5 | D64: 0 | E64: 0.07 | F64: 0.07 | G64: 0.07 | H64: 0.07 | I64: 0.07 | J64: 0.07 | K64: 0.07 | L64: 0.07 | M64: 0.07 | N64: 0.03 | O64: 0.03 | P64: 0.03 | Q64: 0.03 | R64: 0.03 | S64: 0.03 | T64: 0.03 | U64: 0.02 | V64: 0.02 | W64: 0.02 | X64: 0.02 | Y64: 0.02 | Z64: 0.02 | AA64: 0.02 | AB64: 0.02 | BO64: =ROUND($BO27*E64,0) -> 10 | BP64: =ROUND($BO27*F64,0) -> 10 | BQ64: =ROUND($BO27*G64,0) -> 10 | BR64: =ROUND($BO27*H64,0) -> 10 | BS64: =ROUND($BO27*I64,0) -> 10 | BT64: =ROUND($BO27*J64,0) -> 10 | BU64: =ROUND($BO27*K64,0) -> 10 | BV64: =ROUND($BO27*L64,0) -> 10 | ... DJ64: =ROUND($BO27*AZ64,0) -> 0
B65: Week | C65: 5 | D65: 1 – 19 | E65: 0.02 | F65: 0.02 | G65: 0.02 | H65: 0.02 | I65: 0.08 | J65: 0.08 | K65: 0.07 | L65: 0.07 | M65: 0.06 | N65: 0.06 | O65: 0.05 | P65: 0.05 | Q65: 0.05 | R65: 0.04 | S65: 0.04 | T65: 0.04 | U65: 0.04 | V65: 0.03 | W65: 0.03 | X65: 0.03 | Y65: 0.03 | Z65: 0.03 | AA65: 0.02 | AB65: 0.02 | BO65: =ROUND($BO28*E65,0) -> 0 | BP65: =ROUND($BO28*F65,0) -> 0 | BQ65: =ROUND($BO28*G65,0) -> 0 | BR65: =ROUND($BO28*H65,0) -> 0 | BS65: =ROUND($BO28*I65,0) -> 1 | BT65: =ROUND($BO28*J65,0) -> 1 | BU65: =ROUND($BO28*K65,0) -> 1 | BV65: =ROUND($BO28*L65,0) -> 1 | ... DJ65: =ROUND($BO28*AZ65,0) -> 0
B66: Week | C66: 5 | D66: 20 – 29 | H66: 0.08 | I66: 0.08 | J66: 0.07 | K66: 0.07 | L66: 0.06 | M66: 0.06 | N66: 0.05 | O66: 0.05 | P66: 0.05 | Q66: 0.04 | R66: 0.04 | S66: 0.04 | T66: 0.04 | U66: 0.03 | V66: 0.03 | W66: 0.03 | X66: 0.03 | Y66: 0.03 | Z66: 0.02 | AA66: 0.02 | AB66: 0.03 | AC66: 0.03 | AD66: 0.02 | BO66: =ROUND($BO29*E66,0) -> 0 | BP66: =ROUND($BO29*F66,0) -> 0 | BQ66: =ROUND($BO29*G66,0) -> 0 | BR66: =ROUND($BO29*H66,0) -> 2 | BS66: =ROUND($BO29*I66,0) -> 2 | BT66: =ROUND($BO29*J66,0) -> 2 | BU66: =ROUND($BO29*K66,0) -> 2 | BV66: =ROUND($BO29*L66,0) -> 2 | ... DJ66: =ROUND($BO29*AZ66,0) -> 0
B67: Week | C67: 5 | D67: 30 – 39 | J67: 0.08 | K67: 0.08 | L67: 0.07 | M67: 0.07 | N67: 0.06 | O67: 0.06 | P67: 0.05 | Q67: 0.05 | R67: 0.05 | S67: 0.04 | T67: 0.04 | U67: 0.04 | V67: 0.04 | W67: 0.03 | X67: 0.03 | Y67: 0.03 | Z67: 0.03 | AA67: 0.03 | AB67: 0.02 | AC67: 0.02 | AD67: 0.03 | BO67: =ROUND($BO30*E67,0) -> 0 | BP67: =ROUND($BO30*F67,0) -> 0 | BQ67: =ROUND($BO30*G67,0) -> 0 | BR67: =ROUND($BO30*H67,0) -> 0 | BS67: =ROUND($BO30*I67,0) -> 0 | BT67: =ROUND($BO30*J67,0) -> 0 | BU67: =ROUND($BO30*K67,0) -> 0 | BV67: =ROUND($BO30*L67,0) -> 0 | ... DJ67: =ROUND($BO30*AZ67,0) -> 0
B68: Week | C68: 5 | D68: 40 – 49 | K68: 0.08 | L68: 0.08 | M68: 0.07 | N68: 0.07 | O68: 0.06 | P68: 0.06 | Q68: 0.05 | R68: 0.05 | S68: 0.05 | T68: 0.04 | U68: 0.04 | V68: 0.04 | W68: 0.04 | X68: 0.03 | Y68: 0.03 | Z68: 0.03 | AA68: 0.03 | AB68: 0.03 | AC68: 0.02 | AD68: 0.02 | BO68: =ROUND($BO31*E68,0) -> 0 | BP68: =ROUND($BO31*F68,0) -> 0 | BQ68: =ROUND($BO31*G68,0) -> 0 | BR68: =ROUND($BO31*H68,0) -> 0 | BS68: =ROUND($BO31*I68,0) -> 0 | BT68: =ROUND($BO31*J68,0) -> 0 | BU68: =ROUND($BO31*K68,0) -> 0 | BV68: =ROUND($BO31*L68,0) -> 0 | ... DJ68: =ROUND($BO31*AZ68,0) -> 0
B69: Week | C69: 5 | D69: 50+ | L69: 0.08 | M69: 0.08 | N69: 0.07 | O69: 0.07 | P69: 0.06 | Q69: 0.06 | R69: 0.05 | S69: 0.05 | T69: 0.05 | U69: 0.04 | V69: 0.04 | W69: 0.04 | X69: 0.04 | Y69: 0.03 | Z69: 0.03 | AA69: 0.03 | AB69: 0.03 | AC69: 0.03 | AD69: 0.02 | BO69: =ROUND($BO32*E69,0) -> 0 | BP69: =ROUND($BO32*F69,0) -> 0 | BQ69: =ROUND($BO32*G69,0) -> 0 | BR69: =ROUND($BO32*H69,0) -> 0 | BS69: =ROUND($BO32*I69,0) -> 0 | BT69: =ROUND($BO32*J69,0) -> 0 | BU69: =ROUND($BO32*K69,0) -> 0 | BV69: =ROUND($BO32*L69,0) -> 1 | ... DJ69: =ROUND($BO32*AZ69,0) -> 0
B70: Week | C70: 5 | D70: Deductible Remaining | N70: 0.08 | O70: 0.08 | P70: 0.07 | Q70: 0.07 | R70: 0.06 | S70: 0.06 | T70: 0.05 | U70: 0.05 | V70: 0.05 | W70: 0.04 | X70: 0.04 | Y70: 0.04 | Z70: 0.04 | AA70: 0.03 | AB70: 0.03 | AC70: 0.03 | AD70: 0.03 | BO70: =ROUND($BO33*E70,0) -> 0 | BP70: =ROUND($BO33*F70,0) -> 0 | BQ70: =ROUND($BO33*G70,0) -> 0 | BR70: =ROUND($BO33*H70,0) -> 0 | BS70: =ROUND($BO33*I70,0) -> 0 | BT70: =ROUND($BO33*J70,0) -> 0 | BU70: =ROUND($BO33*K70,0) -> 0 | BV70: =ROUND($BO33*L70,0) -> 0 | ... DJ70: =ROUND($BO33*AZ70,0) -> 0
B71: Week | C71: 6 | D71: 0 | E71: 0.07 | F71: 0.07 | G71: 0.07 | H71: 0.07 | I71: 0.07 | J71: 0.07 | K71: 0.07 | L71: 0.07 | M71: 0.07 | N71: 0.03 | O71: 0.03 | P71: 0.03 | Q71: 0.03 | R71: 0.03 | S71: 0.03 | T71: 0.03 | U71: 0.02 | V71: 0.02 | W71: 0.02 | X71: 0.02 | Y71: 0.02 | Z71: 0.02 | AA71: 0.02 | AB71: 0.02 | BP71: =ROUND($BP27*E71,0) -> 10 | BQ71: =ROUND($BP27*F71,0) -> 10 | BR71: =ROUND($BP27*G71,0) -> 10 | BS71: =ROUND($BP27*H71,0) -> 10 | BT71: =ROUND($BP27*I71,0) -> 10 | BU71: =ROUND($BP27*J71,0) -> 10 | BV71: =ROUND($BP27*K71,0) -> 10 | BW71: =ROUND($BP27*L71,0) -> 10 | ... DJ71: =ROUND($BP27*AY71,0) -> 0
B72: Week | C72: 6 | D72: 1 – 19 | E72: 0.02 | F72: 0.02 | G72: 0.02 | H72: 0.02 | I72: 0.08 | J72: 0.08 | K72: 0.07 | L72: 0.07 | M72: 0.06 | N72: 0.06 | O72: 0.05 | P72: 0.05 | Q72: 0.05 | R72: 0.04 | S72: 0.04 | T72: 0.04 | U72: 0.04 | V72: 0.03 | W72: 0.03 | X72: 0.03 | Y72: 0.03 | Z72: 0.03 | AA72: 0.02 | AB72: 0.02 | BP72: =ROUND($BP28*E72,0) -> 0 | BQ72: =ROUND($BP28*F72,0) -> 0 | BR72: =ROUND($BP28*G72,0) -> 0 | BS72: =ROUND($BP28*H72,0) -> 0 | BT72: =ROUND($BP28*I72,0) -> 1 | BU72: =ROUND($BP28*J72,0) -> 1 | BV72: =ROUND($BP28*K72,0) -> 1 | BW72: =ROUND($BP28*L72,0) -> 1 | ... DJ72: =ROUND($BP28*AY72,0) -> 0
B73: Week | C73: 6 | D73: 20 – 29 | H73: 0.08 | I73: 0.08 | J73: 0.07 | K73: 0.07 | L73: 0.06 | M73: 0.06 | N73: 0.05 | O73: 0.05 | P73: 0.05 | Q73: 0.04 | R73: 0.04 | S73: 0.04 | T73: 0.04 | U73: 0.03 | V73: 0.03 | W73: 0.03 | X73: 0.03 | Y73: 0.03 | Z73: 0.02 | AA73: 0.02 | AB73: 0.03 | AC73: 0.03 | AD73: 0.02 | BP73: =ROUND($BP29*E73,0) -> 0 | BQ73: =ROUND($BP29*F73,0) -> 0 | BR73: =ROUND($BP29*G73,0) -> 0 | BS73: =ROUND($BP29*H73,0) -> 2 | BT73: =ROUND($BP29*I73,0) -> 2 | BU73: =ROUND($BP29*J73,0) -> 2 | BV73: =ROUND($BP29*K73,0) -> 2 | BW73: =ROUND($BP29*L73,0) -> 2 | ... DJ73: =ROUND($BP29*AY73,0) -> 0
B74: Week | C74: 6 | D74: 30 – 39 | J74: 0.08 | K74: 0.08 | L74: 0.07 | M74: 0.07 | N74: 0.06 | O74: 0.06 | P74: 0.05 | Q74: 0.05 | R74: 0.05 | S74: 0.04 | T74: 0.04 | U74: 0.04 | V74: 0.04 | W74: 0.03 | X74: 0.03 | Y74: 0.03 | Z74: 0.03 | AA74: 0.03 | AB74: 0.02 | AC74: 0.02 | AD74: 0.03 | BP74: =ROUND($BP30*E74,0) -> 0 | BQ74: =ROUND($BP30*F74,0) -> 0 | BR74: =ROUND($BP30*G74,0) -> 0 | BS74: =ROUND($BP30*H74,0) -> 0 | BT74: =ROUND($BP30*I74,0) -> 0 | BU74: =ROUND($BP30*J74,0) -> 0 | BV74: =ROUND($BP30*K74,0) -> 0 | BW74: =ROUND($BP30*L74,0) -> 0 | ... DJ74: =ROUND($BP30*AY74,0) -> 0
B75: Week | C75: 6 | D75: 40 – 49 | K75: 0.08 | L75: 0.08 | M75: 0.07 | N75: 0.07 | O75: 0.06 | P75: 0.06 | Q75: 0.05 | R75: 0.05 | S75: 0.05 | T75: 0.04 | U75: 0.04 | V75: 0.04 | W75: 0.04 | X75: 0.03 | Y75: 0.03 | Z75: 0.03 | AA75: 0.03 | AB75: 0.03 | AC75: 0.02 | AD75: 0.02 | BP75: =ROUND($BP31*E75,0) -> 0 | BQ75: =ROUND($BP31*F75,0) -> 0 | BR75: =ROUND($BP31*G75,0) -> 0 | BS75: =ROUND($BP31*H75,0) -> 0 | BT75: =ROUND($BP31*I75,0) -> 0 | BU75: =ROUND($BP31*J75,0) -> 0 | BV75: =ROUND($BP31*K75,0) -> 0 | BW75: =ROUND($BP31*L75,0) -> 0 | ... DJ75: =ROUND($BP31*AY75,0) -> 0
B76: Week | C76: 6 | D76: 50+ | L76: 0.08 | M76: 0.08 | N76: 0.07 | O76: 0.07 | P76: 0.06 | Q76: 0.06 | R76: 0.05 | S76: 0.05 | T76: 0.05 | U76: 0.04 | V76: 0.04 | W76: 0.04 | X76: 0.04 | Y76: 0.03 | Z76: 0.03 | AA76: 0.03 | AB76: 0.03 | AC76: 0.03 | AD76: 0.02 | BP76: =ROUND($BP32*E76,0) -> 0 | BQ76: =ROUND($BP32*F76,0) -> 0 | BR76: =ROUND($BP32*G76,0) -> 0 | BS76: =ROUND($BP32*H76,0) -> 0 | BT76: =ROUND($BP32*I76,0) -> 0 | BU76: =ROUND($BP32*J76,0) -> 0 | BV76: =ROUND($BP32*K76,0) -> 0 | BW76: =ROUND($BP32*L76,0) -> 1 | ... DJ76: =ROUND($BP32*AY76,0) -> 0
B77: Week | C77: 6 | D77: Deductible Remaining | N77: 0.08 | O77: 0.08 | P77: 0.07 | Q77: 0.07 | R77: 0.06 | S77: 0.06 | T77: 0.05 | U77: 0.05 | V77: 0.05 | W77: 0.04 | X77: 0.04 | Y77: 0.04 | Z77: 0.04 | AA77: 0.03 | AB77: 0.03 | AC77: 0.03 | AD77: 0.03 | BP77: =ROUND($BP33*E77,0) -> 0 | BQ77: =ROUND($BP33*F77,0) -> 0 | BR77: =ROUND($BP33*G77,0) -> 0 | BS77: =ROUND($BP33*H77,0) -> 0 | BT77: =ROUND($BP33*I77,0) -> 0 | BU77: =ROUND($BP33*J77,0) -> 0 | BV77: =ROUND($BP33*K77,0) -> 0 | BW77: =ROUND($BP33*L77,0) -> 0 | ... DJ77: =ROUND($BP33*AY77,0) -> 0
B78: Week | C78: 7 | D78: 0 | E78: 0.07 | F78: 0.07 | G78: 0.07 | H78: 0.07 | I78: 0.07 | J78: 0.07 | K78: 0.07 | L78: 0.07 | M78: 0.07 | N78: 0.03 | O78: 0.03 | P78: 0.03 | Q78: 0.03 | R78: 0.03 | S78: 0.03 | T78: 0.03 | U78: 0.02 | V78: 0.02 | W78: 0.02 | X78: 0.02 | Y78: 0.02 | Z78: 0.02 | AA78: 0.02 | AB78: 0.02 | BQ78: =ROUND($BQ27*E78,0) -> 10 | BR78: =ROUND($BQ27*F78,0) -> 10 | BS78: =ROUND($BQ27*G78,0) -> 10 | BT78: =ROUND($BQ27*H78,0) -> 10 | BU78: =ROUND($BQ27*I78,0) -> 10 | BV78: =ROUND($BQ27*J78,0) -> 10 | BW78: =ROUND($BQ27*K78,0) -> 10 | BX78: =ROUND($BQ27*L78,0) -> 10 | ... DJ78: =ROUND($BQ27*AX78,0) -> 0
B79: Week | C79: 7 | D79: 1 – 19 | E79: 0.02 | F79: 0.02 | G79: 0.02 | H79: 0.02 | I79: 0.08 | J79: 0.08 | K79: 0.07 | L79: 0.07 | M79: 0.06 | N79: 0.06 | O79: 0.05 | P79: 0.05 | Q79: 0.05 | R79: 0.04 | S79: 0.04 | T79: 0.04 | U79: 0.04 | V79: 0.03 | W79: 0.03 | X79: 0.03 | Y79: 0.03 | Z79: 0.03 | AA79: 0.02 | AB79: 0.02 | BQ79: =ROUND($BQ28*E79,0) -> 0 | BR79: =ROUND($BQ28*F79,0) -> 0 | BS79: =ROUND($BQ28*G79,0) -> 0 | BT79: =ROUND($BQ28*H79,0) -> 0 | BU79: =ROUND($BQ28*I79,0) -> 1 | BV79: =ROUND($BQ28*J79,0) -> 1 | BW79: =ROUND($BQ28*K79,0) -> 1 | BX79: =ROUND($BQ28*L79,0) -> 1 | ... DJ79: =ROUND($BQ28*AX79,0) -> 0
B80: Week | C80: 7 | D80: 20 – 29 | H80: 0.08 | I80: 0.08 | J80: 0.07 | K80: 0.07 | L80: 0.06 | M80: 0.06 | N80: 0.05 | O80: 0.05 | P80: 0.05 | Q80: 0.04 | R80: 0.04 | S80: 0.04 | T80: 0.04 | U80: 0.03 | V80: 0.03 | W80: 0.03 | X80: 0.03 | Y80: 0.03 | Z80: 0.02 | AA80: 0.02 | AB80: 0.03 | AC80: 0.03 | AD80: 0.02 | BQ80: =ROUND($BQ29*E80,0) -> 0 | BR80: =ROUND($BQ29*F80,0) -> 0 | BS80: =ROUND($BQ29*G80,0) -> 0 | BT80: =ROUND($BQ29*H80,0) -> 2 | BU80: =ROUND($BQ29*I80,0) -> 2 | BV80: =ROUND($BQ29*J80,0) -> 2 | BW80: =ROUND($BQ29*K80,0) -> 2 | BX80: =ROUND($BQ29*L80,0) -> 2 | ... DJ80: =ROUND($BQ29*AX80,0) -> 0
B81: Week | C81: 7 | D81: 30 – 39 | J81: 0.08 | K81: 0.08 | L81: 0.07 | M81: 0.07 | N81: 0.06 | O81: 0.06 | P81: 0.05 | Q81: 0.05 | R81: 0.05 | S81: 0.04 | T81: 0.04 | U81: 0.04 | V81: 0.04 | W81: 0.03 | X81: 0.03 | Y81: 0.03 | Z81: 0.03 | AA81: 0.03 | AB81: 0.02 | AC81: 0.02 | AD81: 0.03 | BQ81: =ROUND($BQ30*E81,0) -> 0 | BR81: =ROUND($BQ30*F81,0) -> 0 | BS81: =ROUND($BQ30*G81,0) -> 0 | BT81: =ROUND($BQ30*H81,0) -> 0 | BU81: =ROUND($BQ30*I81,0) -> 0 | BV81: =ROUND($BQ30*J81,0) -> 0 | BW81: =ROUND($BQ30*K81,0) -> 0 | BX81: =ROUND($BQ30*L81,0) -> 0 | ... DJ81: =ROUND($BQ30*AX81,0) -> 0
B82: Week | C82: 7 | D82: 40 – 49 | K82: 0.08 | L82: 0.08 | M82: 0.07 | N82: 0.07 | O82: 0.06 | P82: 0.06 | Q82: 0.05 | R82: 0.05 | S82: 0.05 | T82: 0.04 | U82: 0.04 | V82: 0.04 | W82: 0.04 | X82: 0.03 | Y82: 0.03 | Z82: 0.03 | AA82: 0.03 | AB82: 0.03 | AC82: 0.02 | AD82: 0.02 | BQ82: =ROUND($BQ31*E82,0) -> 0 | BR82: =ROUND($BQ31*F82,0) -> 0 | BS82: =ROUND($BQ31*G82,0) -> 0 | BT82: =ROUND($BQ31*H82,0) -> 0 | BU82: =ROUND($BQ31*I82,0) -> 0 | BV82: =ROUND($BQ31*J82,0) -> 0 | BW82: =ROUND($BQ31*K82,0) -> 0 | BX82: =ROUND($BQ31*L82,0) -> 0 | ... DJ82: =ROUND($BQ31*AX82,0) -> 0
B83: Week | C83: 7 | D83: 50+ | L83: 0.08 | M83: 0.08 | N83: 0.07 | O83: 0.07 | P83: 0.06 | Q83: 0.06 | R83: 0.05 | S83: 0.05 | T83: 0.05 | U83: 0.04 | V83: 0.04 | W83: 0.04 | X83: 0.04 | Y83: 0.03 | Z83: 0.03 | AA83: 0.03 | AB83: 0.03 | AC83: 0.03 | AD83: 0.02 | BQ83: =ROUND($BQ32*E83,0) -> 0 | BR83: =ROUND($BQ32*F83,0) -> 0 | BS83: =ROUND($BQ32*G83,0) -> 0 | BT83: =ROUND($BQ32*H83,0) -> 0 | BU83: =ROUND($BQ32*I83,0) -> 0 | BV83: =ROUND($BQ32*J83,0) -> 0 | BW83: =ROUND($BQ32*K83,0) -> 0 | BX83: =ROUND($BQ32*L83,0) -> 1 | ... DJ83: =ROUND($BQ32*AX83,0) -> 0
B84: Week | C84: 7 | D84: Deductible Remaining | N84: 0.08 | O84: 0.08 | P84: 0.07 | Q84: 0.07 | R84: 0.06 | S84: 0.06 | T84: 0.05 | U84: 0.05 | V84: 0.05 | W84: 0.04 | X84: 0.04 | Y84: 0.04 | Z84: 0.04 | AA84: 0.03 | AB84: 0.03 | AC84: 0.03 | AD84: 0.03 | BQ84: =ROUND($BQ33*E84,0) -> 0 | BR84: =ROUND($BQ33*F84,0) -> 0 | BS84: =ROUND($BQ33*G84,0) -> 0 | BT84: =ROUND($BQ33*H84,0) -> 0 | BU84: =ROUND($BQ33*I84,0) -> 0 | BV84: =ROUND($BQ33*J84,0) -> 0 | BW84: =ROUND($BQ33*K84,0) -> 0 | BX84: =ROUND($BQ33*L84,0) -> 0 | ... DJ84: =ROUND($BQ33*AX84,0) -> 0
B85: Week | C85: 8 | D85: 0 | E85: 0.07 | F85: 0.07 | G85: 0.07 | H85: 0.07 | I85: 0.07 | J85: 0.07 | K85: 0.07 | L85: 0.07 | M85: 0.07 | N85: 0.03 | O85: 0.03 | P85: 0.03 | Q85: 0.03 | R85: 0.03 | S85: 0.03 | T85: 0.03 | U85: 0.02 | V85: 0.02 | W85: 0.02 | X85: 0.02 | Y85: 0.02 | Z85: 0.02 | AA85: 0.02 | AB85: 0.02 | BR85: =ROUND($BR27*E85,0) -> 10 | BS85: =ROUND($BR27*F85,0) -> 10 | BT85: =ROUND($BR27*G85,0) -> 10 | BU85: =ROUND($BR27*H85,0) -> 10 | BV85: =ROUND($BR27*I85,0) -> 10 | BW85: =ROUND($BR27*J85,0) -> 10 | BX85: =ROUND($BR27*K85,0) -> 10 | BY85: =ROUND($BR27*L85,0) -> 10 | ... DJ85: =ROUND($BR27*AW85,0) -> 0
B86: Week | C86: 8 | D86: 1 – 19 | E86: 0.02 | F86: 0.02 | G86: 0.02 | H86: 0.02 | I86: 0.08 | J86: 0.08 | K86: 0.07 | L86: 0.07 | M86: 0.06 | N86: 0.06 | O86: 0.05 | P86: 0.05 | Q86: 0.05 | R86: 0.04 | S86: 0.04 | T86: 0.04 | U86: 0.04 | V86: 0.03 | W86: 0.03 | X86: 0.03 | Y86: 0.03 | Z86: 0.03 | AA86: 0.02 | AB86: 0.02 | BR86: =ROUND($BR28*E86,0) -> 0 | BS86: =ROUND($BR28*F86,0) -> 0 | BT86: =ROUND($BR28*G86,0) -> 0 | BU86: =ROUND($BR28*H86,0) -> 0 | BV86: =ROUND($BR28*I86,0) -> 1 | BW86: =ROUND($BR28*J86,0) -> 1 | BX86: =ROUND($BR28*K86,0) -> 1 | BY86: =ROUND($BR28*L86,0) -> 1 | ... DJ86: =ROUND($BR28*AW86,0) -> 0
B87: Week | C87: 8 | D87: 20 – 29 | H87: 0.08 | I87: 0.08 | J87: 0.07 | K87: 0.07 | L87: 0.06 | M87: 0.06 | N87: 0.05 | O87: 0.05 | P87: 0.05 | Q87: 0.04 | R87: 0.04 | S87: 0.04 | T87: 0.04 | U87: 0.03 | V87: 0.03 | W87: 0.03 | X87: 0.03 | Y87: 0.03 | Z87: 0.02 | AA87: 0.02 | AB87: 0.03 | AC87: 0.03 | AD87: 0.02 | BR87: =ROUND($BR29*E87,0) -> 0 | BS87: =ROUND($BR29*F87,0) -> 0 | BT87: =ROUND($BR29*G87,0) -> 0 | BU87: =ROUND($BR29*H87,0) -> 2 | BV87: =ROUND($BR29*I87,0) -> 2 | BW87: =ROUND($BR29*J87,0) -> 2 | BX87: =ROUND($BR29*K87,0) -> 2 | BY87: =ROUND($BR29*L87,0) -> 2 | ... DJ87: =ROUND($BR29*AW87,0) -> 0
B88: Week | C88: 8 | D88: 30 – 39 | J88: 0.08 | K88: 0.08 | L88: 0.07 | M88: 0.07 | N88: 0.06 | O88: 0.06 | P88: 0.05 | Q88: 0.05 | R88: 0.05 | S88: 0.04 | T88: 0.04 | U88: 0.04 | V88: 0.04 | W88: 0.03 | X88: 0.03 | Y88: 0.03 | Z88: 0.03 | AA88: 0.03 | AB88: 0.02 | AC88: 0.02 | AD88: 0.03 | AE88: 0.03 | AF88: 0.02 | BR88: =ROUND($BR30*E88,0) -> 0 | BS88: =ROUND($BR30*F88,0) -> 0 | BT88: =ROUND($BR30*G88,0) -> 0 | BU88: =ROUND($BR30*H88,0) -> 0 | BV88: =ROUND($BR30*I88,0) -> 0 | BW88: =ROUND($BR30*J88,0) -> 0 | BX88: =ROUND($BR30*K88,0) -> 0 | BY88: =ROUND($BR30*L88,0) -> 0 | ... DJ88: =ROUND($BR30*AW88,0) -> 0
B89: Week | C89: 8 | D89: 40 – 49 | K89: 0.08 | L89: 0.08 | M89: 0.07 | N89: 0.07 | O89: 0.06 | P89: 0.06 | Q89: 0.05 | R89: 0.05 | S89: 0.05 | T89: 0.04 | U89: 0.04 | V89: 0.04 | W89: 0.04 | X89: 0.03 | Y89: 0.03 | Z89: 0.03 | AA89: 0.03 | AB89: 0.03 | AC89: 0.02 | AD89: 0.02 | AE89: 0.03 | AF89: 0.03 | AG89: 0.02 | BR89: =ROUND($BR31*E89,0) -> 0 | BS89: =ROUND($BR31*F89,0) -> 0 | BT89: =ROUND($BR31*G89,0) -> 0 | BU89: =ROUND($BR31*H89,0) -> 0 | BV89: =ROUND($BR31*I89,0) -> 0 | BW89: =ROUND($BR31*J89,0) -> 0 | BX89: =ROUND($BR31*K89,0) -> 0 | BY89: =ROUND($BR31*L89,0) -> 0 | ... DJ89: =ROUND($BR31*AW89,0) -> 0
B90: Week | C90: 8 | D90: 50+ | L90: 0.08 | M90: 0.08 | N90: 0.07 | O90: 0.07 | P90: 0.06 | Q90: 0.06 | R90: 0.05 | S90: 0.05 | T90: 0.05 | U90: 0.04 | V90: 0.04 | W90: 0.04 | X90: 0.04 | Y90: 0.03 | Z90: 0.03 | AA90: 0.03 | AB90: 0.03 | AC90: 0.03 | AD90: 0.02 | AE90: 0.02 | AF90: 0.03 | AG90: 0.03 | AH90: 0.02 | BR90: =ROUND($BR32*E90,0) -> 0 | BS90: =ROUND($BR32*F90,0) -> 0 | BT90: =ROUND($BR32*G90,0) -> 0 | BU90: =ROUND($BR32*H90,0) -> 0 | BV90: =ROUND($BR32*I90,0) -> 0 | BW90: =ROUND($BR32*J90,0) -> 0 | BX90: =ROUND($BR32*K90,0) -> 0 | BY90: =ROUND($BR32*L90,0) -> 1 | ... DJ90: =ROUND($BR32*AW90,0) -> 0
B91: Week | C91: 8 | D91: Deductible Remaining | N91: 0.08 | O91: 0.08 | P91: 0.07 | Q91: 0.07 | R91: 0.06 | S91: 0.06 | T91: 0.05 | U91: 0.05 | V91: 0.05 | W91: 0.04 | X91: 0.04 | Y91: 0.04 | Z91: 0.04 | AA91: 0.03 | AB91: 0.03 | AC91: 0.03 | AD91: 0.03 | AE91: 0.03 | AF91: 0.02 | AG91: 0.02 | AH91: 0.03 | AI91: 0.03 | AJ91: 0.02 | BR91: =ROUND($BR33*E91,0) -> 0 | BS91: =ROUND($BR33*F91,0) -> 0 | BT91: =ROUND($BR33*G91,0) -> 0 | BU91: =ROUND($BR33*H91,0) -> 0 | BV91: =ROUND($BR33*I91,0) -> 0 | BW91: =ROUND($BR33*J91,0) -> 0 | BX91: =ROUND($BR33*K91,0) -> 0 | BY91: =ROUND($BR33*L91,0) -> 0 | ... DJ91: =ROUND($BR33*AW91,0) -> 0
B92: Week | C92: 9 | D92: 0 | E92: 0.07 | F92: 0.07 | G92: 0.07 | H92: 0.07 | I92: 0.07 | J92: 0.07 | K92: 0.07 | L92: 0.07 | M92: 0.07 | N92: 0.03 | O92: 0.03 | P92: 0.03 | Q92: 0.03 | R92: 0.03 | S92: 0.03 | T92: 0.03 | U92: 0.02 | V92: 0.02 | W92: 0.02 | X92: 0.02 | Y92: 0.02 | Z92: 0.02 | AA92: 0.02 | AB92: 0.02 | BS92: =ROUND($BS27*E92,0) -> 10 | BT92: =ROUND($BS27*F92,0) -> 10 | BU92: =ROUND($BS27*G92,0) -> 10 | BV92: =ROUND($BS27*H92,0) -> 10 | BW92: =ROUND($BS27*I92,0) -> 10 | BX92: =ROUND($BS27*J92,0) -> 10 | BY92: =ROUND($BS27*K92,0) -> 10 | BZ92: =ROUND($BS27*L92,0) -> 10 | ... DJ92: =ROUND($BS27*AV92,0) -> 0
B93: Week | C93: 9 | D93: 1 – 19 | E93: 0.02 | F93: 0.02 | G93: 0.02 | H93: 0.02 | I93: 0.08 | J93: 0.08 | K93: 0.07 | L93: 0.07 | M93: 0.06 | N93: 0.06 | O93: 0.05 | P93: 0.05 | Q93: 0.05 | R93: 0.04 | S93: 0.04 | T93: 0.04 | U93: 0.04 | V93: 0.03 | W93: 0.03 | X93: 0.03 | Y93: 0.03 | Z93: 0.03 | AA93: 0.02 | AB93: 0.02 | BS93: =ROUND($BS28*E93,0) -> 0 | BT93: =ROUND($BS28*F93,0) -> 0 | BU93: =ROUND($BS28*G93,0) -> 0 | BV93: =ROUND($BS28*H93,0) -> 0 | BW93: =ROUND($BS28*I93,0) -> 1 | BX93: =ROUND($BS28*J93,0) -> 1 | BY93: =ROUND($BS28*K93,0) -> 1 | BZ93: =ROUND($BS28*L93,0) -> 1 | ... DJ93: =ROUND($BS28*AV93,0) -> 0
B94: Week | C94: 9 | D94: 20 – 29 | H94: 0.08 | I94: 0.08 | J94: 0.07 | K94: 0.07 | L94: 0.06 | M94: 0.06 | N94: 0.05 | O94: 0.05 | P94: 0.05 | Q94: 0.04 | R94: 0.04 | S94: 0.04 | T94: 0.04 | U94: 0.03 | V94: 0.03 | W94: 0.03 | X94: 0.03 | Y94: 0.03 | Z94: 0.02 | AA94: 0.02 | AB94: 0.03 | AC94: 0.03 | AD94: 0.02 | BS94: =ROUND($BS29*E94,0) -> 0 | BT94: =ROUND($BS29*F94,0) -> 0 | BU94: =ROUND($BS29*G94,0) -> 0 | BV94: =ROUND($BS29*H94,0) -> 2 | BW94: =ROUND($BS29*I94,0) -> 2 | BX94: =ROUND($BS29*J94,0) -> 2 | BY94: =ROUND($BS29*K94,0) -> 2 | BZ94: =ROUND($BS29*L94,0) -> 2 | ... DJ94: =ROUND($BS29*AV94,0) -> 0
B95: Week | C95: 9 | D95: 30 – 39 | J95: 0.08 | K95: 0.08 | L95: 0.07 | M95: 0.07 | N95: 0.06 | O95: 0.06 | P95: 0.05 | Q95: 0.05 | R95: 0.05 | S95: 0.04 | T95: 0.04 | U95: 0.04 | V95: 0.04 | W95: 0.03 | X95: 0.03 | Y95: 0.03 | Z95: 0.03 | AA95: 0.03 | AB95: 0.02 | AC95: 0.02 | AD95: 0.03 | BS95: =ROUND($BS30*E95,0) -> 0 | BT95: =ROUND($BS30*F95,0) -> 0 | BU95: =ROUND($BS30*G95,0) -> 0 | BV95: =ROUND($BS30*H95,0) -> 0 | BW95: =ROUND($BS30*I95,0) -> 0 | BX95: =ROUND($BS30*J95,0) -> 0 | BY95: =ROUND($BS30*K95,0) -> 0 | BZ95: =ROUND($BS30*L95,0) -> 0 | ... DJ95: =ROUND($BS30*AV95,0) -> 0
B96: Week | C96: 9 | D96: 40 – 49 | K96: 0.08 | L96: 0.08 | M96: 0.07 | N96: 0.07 | O96: 0.06 | P96: 0.06 | Q96: 0.05 | R96: 0.05 | S96: 0.05 | T96: 0.04 | U96: 0.04 | V96: 0.04 | W96: 0.04 | X96: 0.03 | Y96: 0.03 | Z96: 0.03 | AA96: 0.03 | AB96: 0.03 | AC96: 0.02 | AD96: 0.02 | BS96: =ROUND($BS31*E96,0) -> 0 | BT96: =ROUND($BS31*F96,0) -> 0 | BU96: =ROUND($BS31*G96,0) -> 0 | BV96: =ROUND($BS31*H96,0) -> 0 | BW96: =ROUND($BS31*I96,0) -> 0 | BX96: =ROUND($BS31*J96,0) -> 0 | BY96: =ROUND($BS31*K96,0) -> 0 | BZ96: =ROUND($BS31*L96,0) -> 0 | ... DJ96: =ROUND($BS31*AV96,0) -> 0
B97: Week | C97: 9 | D97: 50+ | L97: 0.08 | M97: 0.08 | N97: 0.07 | O97: 0.07 | P97: 0.06 | Q97: 0.06 | R97: 0.05 | S97: 0.05 | T97: 0.05 | U97: 0.04 | V97: 0.04 | W97: 0.04 | X97: 0.04 | Y97: 0.03 | Z97: 0.03 | AA97: 0.03 | AB97: 0.03 | AC97: 0.03 | AD97: 0.02 | BS97: =ROUND($BS32*E97,0) -> 0 | BT97: =ROUND($BS32*F97,0) -> 0 | BU97: =ROUND($BS32*G97,0) -> 0 | BV97: =ROUND($BS32*H97,0) -> 0 | BW97: =ROUND($BS32*I97,0) -> 0 | BX97: =ROUND($BS32*J97,0) -> 0 | BY97: =ROUND($BS32*K97,0) -> 0 | BZ97: =ROUND($BS32*L97,0) -> 1 | ... DJ97: =ROUND($BS32*AV97,0) -> 0
B98: Week | C98: 9 | D98: Deductible Remaining | N98: 0.08 | O98: 0.08 | P98: 0.07 | Q98: 0.07 | R98: 0.06 | S98: 0.06 | T98: 0.05 | U98: 0.05 | V98: 0.05 | W98: 0.04 | X98: 0.04 | Y98: 0.04 | Z98: 0.04 | AA98: 0.03 | AB98: 0.03 | AC98: 0.03 | AD98: 0.03 | BS98: =ROUND($BS33*E98,0) -> 0 | BT98: =ROUND($BS33*F98,0) -> 0 | BU98: =ROUND($BS33*G98,0) -> 0 | BV98: =ROUND($BS33*H98,0) -> 0 | BW98: =ROUND($BS33*I98,0) -> 0 | BX98: =ROUND($BS33*J98,0) -> 0 | BY98: =ROUND($BS33*K98,0) -> 0 | BZ98: =ROUND($BS33*L98,0) -> 0 | ... DJ98: =ROUND($BS33*AV98,0) -> 0
B99: Week | C99: 10 | D99: 0 | E99: 0.07 | F99: 0.07 | G99: 0.07 | H99: 0.07 | I99: 0.07 | J99: 0.07 | K99: 0.07 | L99: 0.07 | M99: 0.07 | N99: 0.03 | O99: 0.03 | P99: 0.03 | Q99: 0.03 | R99: 0.03 | S99: 0.03 | T99: 0.03 | U99: 0.02 | V99: 0.02 | W99: 0.02 | X99: 0.02 | Y99: 0.02 | Z99: 0.02 | AA99: 0.02 | AB99: 0.02 | BT99: =ROUND($BT27*E99,0) -> 55 | BU99: =ROUND($BT27*F99,0) -> 55 | BV99: =ROUND($BT27*G99,0) -> 55 | BW99: =ROUND($BT27*H99,0) -> 55 | BX99: =ROUND($BT27*I99,0) -> 55 | BY99: =ROUND($BT27*J99,0) -> 55 | BZ99: =ROUND($BT27*K99,0) -> 55 | CA99: =ROUND($BT27*L99,0) -> 55 | ... DJ99: =ROUND($BT27*AU99,0) -> 0
B100: Week | C100: 10 | D100: 1 – 19 | E100: 0.02 | F100: 0.02 | G100: 0.02 | H100: 0.02 | I100: 0.08 | J100: 0.08 | K100: 0.07 | L100: 0.07 | M100: 0.06 | N100: 0.06 | O100: 0.05 | P100: 0.05 | Q100: 0.05 | R100: 0.04 | S100: 0.04 | T100: 0.04 | U100: 0.04 | V100: 0.03 | W100: 0.03 | X100: 0.03 | Y100: 0.03 | Z100: 0.03 | AA100: 0.02 | AB100: 0.02 | BT100: =ROUND($BT28*E100,0) -> 2 | BU100: =ROUND($BT28*F100,0) -> 2 | BV100: =ROUND($BT28*G100,0) -> 2 | BW100: =ROUND($BT28*H100,0) -> 2 | BX100: =ROUND($BT28*I100,0) -> 6 | BY100: =ROUND($BT28*J100,0) -> 6 | BZ100: =ROUND($BT28*K100,0) -> 6 | CA100: =ROUND($BT28*L100,0) -> 6 | ... DJ100: =ROUND($BT28*AU100,0) -> 0
B101: Week | C101: 10 | D101: 20 – 29 | H101: 0.08 | I101: 0.08 | J101: 0.07 | K101: 0.07 | L101: 0.06 | M101: 0.06 | N101: 0.05 | O101: 0.05 | P101: 0.05 | Q101: 0.04 | R101: 0.04 | S101: 0.04 | T101: 0.04 | U101: 0.03 | V101: 0.03 | W101: 0.03 | X101: 0.03 | Y101: 0.03 | Z101: 0.02 | AA101: 0.02 | AB101: 0.03 | AC101: 0.03 | AD101: 0.02 | BT101: =ROUND($BT29*E101,0) -> 0 | BU101: =ROUND($BT29*F101,0) -> 0 | BV101: =ROUND($BT29*G101,0) -> 0 | BW101: =ROUND($BT29*H101,0) -> 12 | BX101: =ROUND($BT29*I101,0) -> 12 | BY101: =ROUND($BT29*J101,0) -> 10 | BZ101: =ROUND($BT29*K101,0) -> 10 | CA101: =ROUND($BT29*L101,0) -> 9 | ... DJ101: =ROUND($BT29*AU101,0) -> 0
B102: Week | C102: 10 | D102: 30 – 39 | J102: 0.08 | K102: 0.08 | L102: 0.07 | M102: 0.07 | N102: 0.06 | O102: 0.06 | P102: 0.05 | Q102: 0.05 | R102: 0.05 | S102: 0.04 | T102: 0.04 | U102: 0.04 | V102: 0.04 | W102: 0.03 | X102: 0.03 | Y102: 0.03 | Z102: 0.03 | AA102: 0.03 | AB102: 0.02 | AC102: 0.02 | AD102: 0.03 | BT102: =ROUND($BT30*E102,0) -> 0 | BU102: =ROUND($BT30*F102,0) -> 0 | BV102: =ROUND($BT30*G102,0) -> 0 | BW102: =ROUND($BT30*H102,0) -> 0 | BX102: =ROUND($BT30*I102,0) -> 0 | BY102: =ROUND($BT30*J102,0) -> 2 | BZ102: =ROUND($BT30*K102,0) -> 2 | CA102: =ROUND($BT30*L102,0) -> 2 | ... DJ102: =ROUND($BT30*AU102,0) -> 0
B103: Week | C103: 10 | D103: 40 – 49 | K103: 0.08 | L103: 0.08 | M103: 0.07 | N103: 0.07 | O103: 0.06 | P103: 0.06 | Q103: 0.05 | R103: 0.05 | S103: 0.05 | T103: 0.04 | U103: 0.04 | V103: 0.04 | W103: 0.04 | X103: 0.03 | Y103: 0.03 | Z103: 0.03 | AA103: 0.03 | AB103: 0.03 | AC103: 0.02 | AD103: 0.02 | BT103: =ROUND($BT31*E103,0) -> 0 | BU103: =ROUND($BT31*F103,0) -> 0 | BV103: =ROUND($BT31*G103,0) -> 0 | BW103: =ROUND($BT31*H103,0) -> 0 | BX103: =ROUND($BT31*I103,0) -> 0 | BY103: =ROUND($BT31*J103,0) -> 0 | BZ103: =ROUND($BT31*K103,0) -> 2 | CA103: =ROUND($BT31*L103,0) -> 2 | ... DJ103: =ROUND($BT31*AU103,0) -> 0
B104: Week | C104: 10 | D104: 50+ | L104: 0.08 | M104: 0.08 | N104: 0.07 | O104: 0.07 | P104: 0.06 | Q104: 0.06 | R104: 0.05 | S104: 0.05 | T104: 0.05 | U104: 0.04 | V104: 0.04 | W104: 0.04 | X104: 0.04 | Y104: 0.03 | Z104: 0.03 | AA104: 0.03 | AB104: 0.03 | AC104: 0.03 | AD104: 0.02 | BT104: =ROUND($BT32*E104,0) -> 0 | BU104: =ROUND($BT32*F104,0) -> 0 | BV104: =ROUND($BT32*G104,0) -> 0 | BW104: =ROUND($BT32*H104,0) -> 0 | BX104: =ROUND($BT32*I104,0) -> 0 | BY104: =ROUND($BT32*J104,0) -> 0 | BZ104: =ROUND($BT32*K104,0) -> 0 | CA104: =ROUND($BT32*L104,0) -> 4 | ... DJ104: =ROUND($BT32*AU104,0) -> 0
B105: Week | C105: 10 | D105: Deductible Remaining | N105: 0.08 | O105: 0.08 | P105: 0.07 | Q105: 0.07 | R105: 0.06 | S105: 0.06 | T105: 0.05 | U105: 0.05 | V105: 0.05 | W105: 0.04 | X105: 0.04 | Y105: 0.04 | Z105: 0.04 | AA105: 0.03 | AB105: 0.03 | AC105: 0.03 | AD105: 0.03 | BT105: =ROUND($BT33*E105,0) -> 0 | BU105: =ROUND($BT33*F105,0) -> 0 | BV105: =ROUND($BT33*G105,0) -> 0 | BW105: =ROUND($BT33*H105,0) -> 0 | BX105: =ROUND($BT33*I105,0) -> 0 | BY105: =ROUND($BT33*J105,0) -> 0 | BZ105: =ROUND($BT33*K105,0) -> 0 | CA105: =ROUND($BT33*L105,0) -> 0 | ... DJ105: =ROUND($BT33*AU105,0) -> 0
B106: Week | C106: 11 | D106: 0 | E106: 0.07 | F106: 0.07 | G106: 0.07 | H106: 0.07 | I106: 0.07 | J106: 0.07 | K106: 0.07 | L106: 0.07 | M106: 0.07 | N106: 0.03 | O106: 0.03 | P106: 0.03 | Q106: 0.03 | R106: 0.03 | S106: 0.03 | T106: 0.03 | U106: 0.02 | V106: 0.02 | W106: 0.02 | X106: 0.02 | Y106: 0.02 | Z106: 0.02 | AA106: 0.02 | AB106: 0.02 | BU106: =ROUND($BU27*E106,0) -> 0 | BV106: =ROUND($BU27*F106,0) -> 0 | BW106: =ROUND($BU27*G106,0) -> 0 | BX106: =ROUND($BU27*H106,0) -> 0 | BY106: =ROUND($BU27*I106,0) -> 0 | BZ106: =ROUND($BU27*J106,0) -> 0 | CA106: =ROUND($BU27*K106,0) -> 0 | CB106: =ROUND($BU27*L106,0) -> 0 | ... DJ106: =ROUND($BU27*AT106,0) -> 0
B107: Week | C107: 11 | D107: 1 – 19 | E107: 0.02 | F107: 0.02 | G107: 0.02 | H107: 0.02 | I107: 0.08 | J107: 0.08 | K107: 0.07 | L107: 0.07 | M107: 0.06 | N107: 0.06 | O107: 0.05 | P107: 0.05 | Q107: 0.05 | R107: 0.04 | S107: 0.04 | T107: 0.04 | U107: 0.04 | V107: 0.03 | W107: 0.03 | X107: 0.03 | Y107: 0.03 | Z107: 0.03 | AA107: 0.02 | AB107: 0.02 | BU107: =ROUND($BU28*E107,0) -> 0 | BV107: =ROUND($BU28*F107,0) -> 0 | BW107: =ROUND($BU28*G107,0) -> 0 | BX107: =ROUND($BU28*H107,0) -> 0 | BY107: =ROUND($BU28*I107,0) -> 0 | BZ107: =ROUND($BU28*J107,0) -> 0 | CA107: =ROUND($BU28*K107,0) -> 0 | CB107: =ROUND($BU28*L107,0) -> 0 | ... DJ107: =ROUND($BU28*AT107,0) -> 0
...
